[
{"counter":0,"material":[{"id":1727,"uniq":"xxx-3offline-2018-01-27","part":"xxx","proc":1,"numproc":1,"face":"1-1","serial":"00000000rR","workorder":""}],"type":"CloseOut","startofcycle":false,"endUTC":"2018-01-27T01:08:08.6225647Z","loc":"CloseOut","locnum":1,"pal":0,"program":"","result":"","elapsed":"-PT1M","active":"PT0S"},
{"counter":0,"material":[{"id":1717,"uniq":"ccc-2offline-2018-01-26","part":"ccc","proc":2,"numproc":2,"face":"2-1","serial":"00000000rH","workorder":""}],"type":"CloseOut","startofcycle":false,"endUTC":"2018-01-27T01:12:32.7506731Z","loc":"CloseOut","locnum":1,"pal":0,"program":"","result":"","elapsed":"-PT1M","active":"PT0S"},
{"counter":0,"material":[{"id":1720,"uniq":"ccc-2offline-2018-01-26","part":"ccc","proc":2,"numproc":2,"face":"2-1","serial":"00000000rK","workorder":""}],"type":"CloseOut","startofcycle":false,"endUTC":"2018-01-27T01:38:51.9824102Z","loc":"CloseOut","locnum":1,"pal":0,"program":"","result":"","elapsed":"-PT1M","active":"PT0S"},
{"counter":0,"material":[{"id":1723,"uniq":"bbb-1offline-2018-01-27","part":"bbb","proc":2,"numproc":2,"face":"2-1","serial":"00000000rN","workorder":""}],"type":"CloseOut","startofcycle":false,"endUTC":"2018-01-27T02:01:29.771564Z","loc":"CloseOut","locnum":1,"pal":0,"program":"","result":"","elapsed":"-PT1M","active":"PT0S"},
{"counter":0,"material":[{"id":1730,"uniq":"xxx-3offline-2018-01-27","part":"xxx","proc":1,"numproc":1,"face":"1-1","serial":"00000000rU","workorder":""}],"type":"CloseOut","startofcycle":false,"endUTC":"2018-01-27T02:52:10.540379Z","loc":"CloseOut","locnum":1,"pal":0,"program":"","result":"","elapsed":"-PT1M","active":"PT0S"},
{"counter":0,"material":[{"id":1725,"uniq":"zzz-4offline-2018-01-27","part":"zzz","proc":1,"numproc":1,"face":"1-1","serial":"00000000rP","workorder":""}],"type":"CloseOut","startofcycle":false,"endUTC":"2018-01-27T03:05:26.4347348Z","loc":"CloseOut","locnum":1,"pal":0,"program":"","result":"","elapsed":"-PT1M","active":"PT0S"},
{"counter":0,"material":[{"id":1721,"uniq":"ccc-2offline-2018-01-26","part":"ccc","proc":2,"numproc":2,"face":"2-1","serial":"00000000rL","workorder":""}],"type":"CloseOut","startofcycle":false,"endUTC":"2018-01-27T03:16:13.8639405Z","loc":"CloseOut","locnum":1,"pal":0,"program":"","result":"","elapsed":"-PT1M","active":"PT0S"},
{"counter":0,"material":[{"id":1722,"uniq":"ccc-2offline-2018-01-26","part":"ccc","proc":2,"numproc":2,"face":"2-1","serial":"00000000rM","workorder":""}],"type":"CloseOut","startofcycle":false,"endUTC":"2018-01-27T03:39:39.9415223Z","loc":"CloseOut","locnum":1,"pal":0,"program":"","result":"","elapsed":"-PT1M","active":"PT0S"},
{"counter":0,"material":[{"id":1728,"uniq":"bbb-1offline-2018-01-27","part":"bbb","proc":2,"numproc":2,"face":"2-1","serial":"00000000rS","workorder":""}],"type":"CloseOut","startofcycle":false,"endUTC":"2018-01-27T03:46:00.5463823Z","loc":"CloseOut","locnum":1,"pal":0,"program":"","result":"","elapsed":"-PT1M","active":"PT0S"},
{"counter":0,"material":[{"id":1724,"uniq":"bbb-1offline-2018-01-27","part":"bbb","proc":2,"numproc":2,"face":"2-1","serial":"00000000rO","workorder":""}],"type":"CloseOut","startofcycle":false,"endUTC":"2018-01-27T04:28:38.308828Z","loc":"CloseOut","locnum":1,"pal":0,"program":"","result":"","elapsed":"-PT1M","active":"PT0S"},
{"counter":0,"material":[{"id":1734,"uniq":"xxx-3offline-2018-01-27","part":"xxx","proc":1,"numproc":1,"face":"1-1","serial":"00000000rY","workorder":""}],"type":"CloseOut","startofcycle":false,"endUTC":"2018-01-27T04:35:41.5131179Z","loc":"CloseOut","locnum":1,"pal":0,"program":"","result":"","elapsed":"-PT1M","active":"PT0S"},
{"counter":0,"material":[{"id":1733,"uniq":"bbb-1offline-2018-01-27","part":"bbb","proc":2,"numproc":2,"face":"2-1","serial":"00000000rX","workorder":""}],"type":"CloseOut","startofcycle":false,"endUTC":"2018-01-27T05:16:32.7603032Z","loc":"CloseOut","locnum":1,"pal":0,"program":"","result":"","elapsed":"-PT1M","active":"PT0S"},
{"counter":0,"material":[{"id":1729,"uniq":"ccc-2offline-2018-01-26","part":"ccc","proc":2,"numproc":2,"face":"2-1","serial":"00000000rT","workorder":""}],"type":"CloseOut","startofcycle":false,"endUTC":"2018-01-27T05:20:15.5562664Z","loc":"CloseOut","locnum":1,"pal":0,"program":"","result":"","elapsed":"-PT1M","active":"PT0S"},
{"counter":0,"material":[{"id":1740,"uniq":"xxx-3offline-2018-01-27","part":"xxx","proc":1,"numproc":1,"face":"1-1","serial":"00000000s4","workorder":""}],"type":"CloseOut","startofcycle":false,"endUTC":"2018-01-27T05:37:54.3597176Z","loc":"CloseOut","locnum":1,"pal":0,"program":"","result":"","elapsed":"-PT1M","active":"PT0S"},
{"counter":0,"material":[{"id":1732,"uniq":"bbb-1offline-2018-01-27","part":"bbb","proc":2,"numproc":2,"face":"2-1","serial":"00000000rW","workorder":""}],"type":"CloseOut","startofcycle":false,"endUTC":"2018-01-27T06:04:43.3487879Z","loc":"CloseOut","locnum":1,"pal":0,"program":"","result":"","elapsed":"-PT1M","active":"PT0S"},
{"counter":0,"material":[{"id":1726,"uniq":"zzz-4offline-2018-01-27","part":"zzz","proc":1,"numproc":1,"face":"1-1","serial":"00000000rQ","workorder":""}],"type":"CloseOut","startofcycle":false,"endUTC":"2018-01-27T06:23:01.3274904Z","loc":"CloseOut","locnum":1,"pal":0,"program":"","result":"","elapsed":"-PT1M","active":"PT0S"},
{"counter":0,"material":[{"id":1743,"uniq":"xxx-3offline-2018-01-27","part":"xxx","proc":1,"numproc":1,"face":"1-1","serial":"00000000s7","workorder":""}],"type":"CloseOut","startofcycle":false,"endUTC":"2018-01-27T06:53:07.512385Z","loc":"CloseOut","locnum":1,"pal":0,"program":"","result":"","elapsed":"-PT1M","active":"PT0S"},
{"counter":0,"material":[{"id":1738,"uniq":"bbb-1offline-2018-01-27","part":"bbb","proc":2,"numproc":2,"face":"2-1","serial":"00000000s2","workorder":""}],"type":"CloseOut","startofcycle":false,"endUTC":"2018-01-27T06:54:29.1659885Z","loc":"CloseOut","locnum":1,"pal":0,"program":"","result":"","elapsed":"-PT1M","active":"PT0S"},
{"counter":0,"material":[{"id":1731,"uniq":"ccc-2offline-2018-01-26","part":"ccc","proc":2,"numproc":2,"face":"2-1","serial":"00000000rV","workorder":""}],"type":"CloseOut","startofcycle":false,"endUTC":"2018-01-27T07:09:18.2918006Z","loc":"CloseOut","locnum":1,"pal":0,"program":"","result":"","elapsed":"-PT1M","active":"PT0S"},
{"counter":0,"material":[{"id":1739,"uniq":"bbb-1offline-2018-01-27","part":"bbb","proc":2,"numproc":2,"face":"2-1","serial":"00000000s3","workorder":""}],"type":"CloseOut","startofcycle":false,"endUTC":"2018-01-27T07:39:58.079147Z","loc":"CloseOut","locnum":1,"pal":0,"program":"","result":"","elapsed":"-PT1M","active":"PT0S"},
{"counter":0,"material":[{"id":1747,"uniq":"xxx-3offline-2018-01-27","part":"xxx","proc":1,"numproc":1,"face":"1-1","serial":"00000000sb","workorder":""}],"type":"CloseOut","startofcycle":false,"endUTC":"2018-01-27T07:55:08.0894861Z","loc":"CloseOut","locnum":1,"pal":0,"program":"","result":"","elapsed":"-PT1M","active":"PT0S"},
{"counter":0,"material":[{"id":1741,"uniq":"bbb-1offline-2018-01-27","part":"bbb","proc":2,"numproc":2,"face":"2-1","serial":"00000000s5","workorder":""}],"type":"CloseOut","startofcycle":false,"endUTC":"2018-01-27T08:28:34.3185038Z","loc":"CloseOut","locnum":1,"pal":0,"program":"","result":"","elapsed":"-PT1M","active":"PT0S"},
{"counter":0,"material":[{"id":1750,"uniq":"xxx-3offline-2018-01-27","part":"xxx","proc":1,"numproc":1,"face":"1-1","serial":"00000000se","workorder":""}],"type":"CloseOut","startofcycle":false,"endUTC":"2018-01-27T08:58:10.1007881Z","loc":"CloseOut","locnum":1,"pal":0,"program":"","result":"","elapsed":"-PT1M","active":"PT0S"},
{"counter":0,"material":[{"id":1736,"uniq":"ccc-2offline-2018-01-26","part":"ccc","proc":2,"numproc":2,"face":"2-1","serial":"00000000s0","workorder":""}],"type":"CloseOut","startofcycle":false,"endUTC":"2018-01-27T09:02:07.9207485Z","loc":"CloseOut","locnum":1,"pal":0,"program":"","result":"","elapsed":"-PT1M","active":"PT0S"},
{"counter":0,"material":[{"id":1744,"uniq":"bbb-1offline-2018-01-27","part":"bbb","proc":2,"numproc":2,"face":"2-1","serial":"00000000s8","workorder":""}],"type":"CloseOut","startofcycle":false,"endUTC":"2018-01-27T09:15:51.6730223Z","loc":"CloseOut","locnum":1,"pal":0,"program":"","result":"","elapsed":"-PT1M","active":"PT0S"},
{"counter":0,"material":[{"id":1735,"uniq":"zzz-4offline-2018-01-27","part":"zzz","proc":1,"numproc":1,"face":"1-1","serial":"00000000rZ","workorder":""}],"type":"CloseOut","startofcycle":false,"endUTC":"2018-01-27T09:40:43.4235135Z","loc":"CloseOut","locnum":1,"pal":0,"program":"","result":"","elapsed":"-PT1M","active":"PT0S"},
{"counter":0,"material":[{"id":1746,"uniq":"bbb-1offline-2018-01-27","part":"bbb","proc":2,"numproc":2,"face":"2-1","serial":"00000000sa","workorder":""}],"type":"CloseOut","startofcycle":false,"endUTC":"2018-01-27T09:49:27.6445788Z","loc":"CloseOut","locnum":1,"pal":0,"program":"","result":"","elapsed":"-PT1M","active":"PT0S"},
{"counter":0,"material":[{"id":1749,"uniq":"bbb-1offline-2018-01-27","part":"bbb","proc":2,"numproc":2,"face":"2-1","serial":"00000000sd","workorder":""}],"type":"CloseOut","startofcycle":false,"endUTC":"2018-01-27T10:16:31.5655178Z","loc":"CloseOut","locnum":1,"pal":0,"program":"","result":"","elapsed":"-PT1M","active":"PT0S"},
{"counter":0,"material":[{"id":1753,"uniq":"xxx-3offline-2018-01-27","part":"xxx","proc":1,"numproc":1,"face":"1-1","serial":"00000000sh","workorder":""}],"type":"CloseOut","startofcycle":false,"endUTC":"2018-01-27T10:38:19.1711558Z","loc":"CloseOut","locnum":1,"pal":0,"program":"","result":"","elapsed":"-PT1M","active":"PT0S"},
{"counter":0,"material":[{"id":1737,"uniq":"ccc-2offline-2018-01-26","part":"ccc","proc":2,"numproc":2,"face":"2-1","serial":"00000000s1","workorder":""}],"type":"CloseOut","startofcycle":false,"endUTC":"2018-01-27T10:52:03.4349158Z","loc":"CloseOut","locnum":1,"pal":0,"program":"","result":"","elapsed":"-PT1M","active":"PT0S"},
{"counter":0,"material":[{"id":1754,"uniq":"bbb-1offline-2018-01-27","part":"bbb","proc":2,"numproc":2,"face":"2-1","serial":"00000000si","workorder":""}],"type":"CloseOut","startofcycle":false,"endUTC":"2018-01-27T11:15:57.2765316Z","loc":"CloseOut","locnum":1,"pal":0,"program":"","result":"","elapsed":"-PT1M","active":"PT0S"},
{"counter":0,"material":[{"id":1751,"uniq":"bbb-1offline-2018-01-27","part":"bbb","proc":2,"numproc":2,"face":"2-1","serial":"00000000sf","workorder":""}],"type":"CloseOut","startofcycle":false,"endUTC":"2018-01-27T11:34:20.249528Z","loc":"CloseOut","locnum":1,"pal":0,"program":"","result":"","elapsed":"-PT1M","active":"PT0S"},
{"counter":0,"material":[{"id":1757,"uniq":"bbb-1offline-2018-01-27","part":"bbb","proc":2,"numproc":2,"face":"2-1","serial":"00000000sl","workorder":""}],"type":"CloseOut","startofcycle":false,"endUTC":"2018-01-27T12:14:10.4576114Z","loc":"CloseOut","locnum":1,"pal":0,"program":"","result":"","elapsed":"-PT1M","active":"PT0S"},
{"counter":0,"material":[{"id":1742,"uniq":"ccc-2offline-2018-01-26","part":"ccc","proc":2,"numproc":2,"face":"2-1","serial":"00000000s6","workorder":""}],"type":"CloseOut","startofcycle":false,"endUTC":"2018-01-27T12:43:07.6278579Z","loc":"CloseOut","locnum":1,"pal":0,"program":"","result":"","elapsed":"-PT1M","active":"PT0S"},
{"counter":0,"material":[{"id":1756,"uniq":"bbb-1offline-2018-01-27","part":"bbb","proc":2,"numproc":2,"face":"2-1","serial":"00000000sk","workorder":""}],"type":"CloseOut","startofcycle":false,"endUTC":"2018-01-27T12:49:42.7821937Z","loc":"CloseOut","locnum":1,"pal":0,"program":"","result":"","elapsed":"-PT1M","active":"PT0S"},
{"counter":0,"material":[{"id":1745,"uniq":"zzz-4offline-2018-01-27","part":"zzz","proc":1,"numproc":1,"face":"1-1","serial":"00000000s9","workorder":""}],"type":"CloseOut","startofcycle":false,"endUTC":"2018-01-27T12:58:39.8282117Z","loc":"CloseOut","locnum":1,"pal":0,"program":"","result":"","elapsed":"-PT1M","active":"PT0S"},
{"counter":0,"material":[{"id":1760,"uniq":"aaa-0offline-2018-01-27","part":"aaa","proc":2,"numproc":2,"face":"2-1","serial":"00000000so","workorder":""}],"type":"CloseOut","startofcycle":false,"endUTC":"2018-01-27T14:01:05.9981151Z","loc":"CloseOut","locnum":1,"pal":0,"program":"","result":"","elapsed":"-PT1M","active":"PT0S"},
{"counter":0,"material":[{"id":1759,"uniq":"bbb-1offline-2018-01-27","part":"bbb","proc":2,"numproc":2,"face":"2-1","serial":"00000000sn","workorder":""}],"type":"CloseOut","startofcycle":false,"endUTC":"2018-01-27T14:26:57.8501326Z","loc":"CloseOut","locnum":1,"pal":0,"program":"","result":"","elapsed":"-PT1M","active":"PT0S"},
{"counter":0,"material":[{"id":1748,"uniq":"ccc-2offline-2018-01-26","part":"ccc","proc":2,"numproc":2,"face":"2-1","serial":"00000000sc","workorder":""}],"type":"CloseOut","startofcycle":false,"endUTC":"2018-01-27T14:36:30.1767726Z","loc":"CloseOut","locnum":1,"pal":0,"program":"","result":"","elapsed":"-PT1M","active":"PT0S"},
{"counter":0,"material":[{"id":1763,"uniq":"aaa-0offline-2018-01-27","part":"aaa","proc":2,"numproc":2,"face":"2-1","serial":"00000000sr","workorder":""}],"type":"CloseOut","startofcycle":false,"endUTC":"2018-01-27T15:09:11.3822561Z","loc":"CloseOut","locnum":1,"pal":0,"program":"","result":"","elapsed":"-PT1M","active":"PT0S"},
{"counter":0,"material":[{"id":1752,"uniq":"ccc-2offline-2018-01-26","part":"ccc","proc":2,"numproc":2,"face":"2-1","serial":"00000000sg","workorder":""}],"type":"CloseOut","startofcycle":false,"endUTC":"2018-01-27T15:13:18.8101918Z","loc":"CloseOut","locnum":1,"pal":0,"program":"","result":"","elapsed":"-PT1M","active":"PT0S"},
{"counter":0,"material":[{"id":1761,"uniq":"aaa-0offline-2018-01-27","part":"aaa","proc":2,"numproc":2,"face":"2-1","serial":"00000000sp","workorder":""}],"type":"CloseOut","startofcycle":false,"endUTC":"2018-01-27T15:50:37.3526274Z","loc":"CloseOut","locnum":1,"pal":0,"program":"","result":"","elapsed":"-PT1M","active":"PT0S"},
{"counter":0,"material":[{"id":1755,"uniq":"zzz-4offline-2018-01-27","part":"zzz","proc":1,"numproc":1,"face":"1-1","serial":"00000000sj","workorder":""}],"type":"CloseOut","startofcycle":false,"endUTC":"2018-01-27T16:18:13.5821304Z","loc":"CloseOut","locnum":1,"pal":0,"program":"","result":"","elapsed":"-PT1M","active":"PT0S"},
{"counter":0,"material":[{"id":1758,"uniq":"ccc-2offline-2018-01-26","part":"ccc","proc":2,"numproc":2,"face":"2-1","serial":"00000000sm","workorder":""}],"type":"CloseOut","startofcycle":false,"endUTC":"2018-01-27T16:39:05.5773015Z","loc":"CloseOut","locnum":1,"pal":0,"program":"","result":"","elapsed":"-PT1M","active":"PT0S"},
{"counter":0,"material":[{"id":1765,"uniq":"aaa-0offline-2018-01-27","part":"aaa","proc":2,"numproc":2,"face":"2-1","serial":"00000000st","workorder":""}],"type":"CloseOut","startofcycle":false,"endUTC":"2018-01-27T16:42:36.344867Z","loc":"CloseOut","locnum":1,"pal":0,"program":"","result":"","elapsed":"-PT1M","active":"PT0S"},
{"counter":0,"material":[{"id":1766,"uniq":"aaa-0offline-2018-01-27","part":"aaa","proc":2,"numproc":2,"face":"2-1","serial":"00000000su","workorder":""}],"type":"CloseOut","startofcycle":false,"endUTC":"2018-01-27T16:56:34.607242Z","loc":"CloseOut","locnum":1,"pal":0,"program":"","result":"","elapsed":"-PT1M","active":"PT0S"},
{"counter":0,"material":[{"id":1762,"uniq":"ccc-2offline-2018-01-27","part":"ccc","proc":2,"numproc":2,"face":"2-1","serial":"00000000sq","workorder":""}],"type":"CloseOut","startofcycle":false,"endUTC":"2018-01-27T17:14:23.6384782Z","loc":"CloseOut","locnum":1,"pal":0,"program":"","result":"","elapsed":"-PT1M","active":"PT0S"},
{"counter":0,"material":[{"id":1768,"uniq":"aaa-0offline-2018-01-27","part":"aaa","proc":2,"numproc":2,"face":"2-1","serial":"00000000sw","workorder":""}],"type":"CloseOut","startofcycle":false,"endUTC":"2018-01-27T17:15:01.7087927Z","loc":"CloseOut","locnum":1,"pal":0,"program":"","result":"","elapsed":"-PT1M","active":"PT0S"},
{"counter":0,"material":[{"id":1767,"uniq":"ccc-2offline-2018-01-27","part":"ccc","proc":2,"numproc":2,"face":"2-1","serial":"00000000sv","workorder":""}],"type":"CloseOut","startofcycle":false,"endUTC":"2018-01-27T18:42:19.9051391Z","loc":"CloseOut","locnum":1,"pal":0,"program":"","result":"","elapsed":"-PT1M","active":"PT0S"},
{"counter":0,"material":[{"id":1764,"uniq":"zzz-4offline-2018-01-27","part":"zzz","proc":1,"numproc":1,"face":"1-1","serial":"00000000ss","workorder":""}],"type":"CloseOut","startofcycle":false,"endUTC":"2018-01-27T19:35:57.3823178Z","loc":"CloseOut","locnum":1,"pal":0,"program":"","result":"","elapsed":"-PT1M","active":"PT0S"},
{"counter":0,"material":[{"id":1770,"uniq":"zzz-4offline-2018-01-27","part":"zzz","proc":1,"numproc":1,"face":"1-1","serial":"00000000sy","workorder":""}],"type":"CloseOut","startofcycle":false,"endUTC":"2018-01-27T20:29:18.7933133Z","loc":"CloseOut","locnum":1,"pal":0,"program":"","result":"","elapsed":"-PT1M","active":"PT0S"},
{"counter":0,"material":[{"id":1769,"uniq":"ccc-2offline-2018-01-27","part":"ccc","proc":2,"numproc":2,"face":"2-1","serial":"00000000sx","workorder":""}],"type":"CloseOut","startofcycle":false,"endUTC":"2018-01-27T20:32:10.7473612Z","loc":"CloseOut","locnum":1,"pal":0,"program":"","result":"","elapsed":"-PT1M","active":"PT0S"},
{"counter":0,"material":[{"id":1771,"uniq":"ccc-2offline-2018-01-27","part":"ccc","proc":2,"numproc":2,"face":"2-1","serial":"00000000sz","workorder":""}],"type":"CloseOut","startofcycle":false,"endUTC":"2018-01-27T22:25:24.0242545Z","loc":"CloseOut","locnum":1,"pal":0,"program":"","result":"","elapsed":"-PT1M","active":"PT0S"},
{"counter":0,"material":[{"id":1772,"uniq":"ccc-2offline-2018-01-27","part":"ccc","proc":2,"numproc":2,"face":"2-1","serial":"00000000sA","workorder":""}],"type":"CloseOut","startofcycle":false,"endUTC":"2018-01-27T22:35:35.5235054Z","loc":"CloseOut","locnum":1,"pal":0,"program":"","result":"","elapsed":"-PT1M","active":"PT0S"},
{"counter":0,"material":[{"id":1774,"uniq":"zzz-4offline-2018-01-27","part":"zzz","proc":1,"numproc":1,"face":"1-1","serial":"00000000sC","workorder":""}],"type":"CloseOut","startofcycle":false,"endUTC":"2018-01-27T23:01:21.4855504Z","loc":"CloseOut","locnum":1,"pal":0,"program":"","result":"","elapsed":"-PT1M","active":"PT0S"},
{"counter":0,"material":[{"id":1776,"uniq":"zzz-4offline-2018-01-27","part":"zzz","proc":1,"numproc":1,"face":"1-1","serial":"00000000sE","workorder":""}],"type":"CloseOut","startofcycle":false,"endUTC":"2018-01-27T23:49:28.6577206Z","loc":"CloseOut","locnum":1,"pal":0,"program":"","result":"","elapsed":"-PT1M","active":"PT0S"},
{"counter":0,"material":[{"id":1773,"uniq":"ccc-2offline-2018-01-27","part":"ccc","proc":2,"numproc":2,"face":"2-1","serial":"00000000sB","workorder":""}],"type":"CloseOut","startofcycle":false,"endUTC":"2018-01-28T00:26:29.8207168Z","loc":"CloseOut","locnum":1,"pal":0,"program":"","result":"","elapsed":"-PT1M","active":"PT0S"},
{"counter":0,"material":[{"id":1775,"uniq":"ccc-2offline-2018-01-27","part":"ccc","proc":2,"numproc":2,"face":"2-1","serial":"00000000sD","workorder":""}],"type":"CloseOut","startofcycle":false,"endUTC":"2018-01-28T01:01:05.0402392Z","loc":"CloseOut","locnum":1,"pal":0,"program":"","result":"","elapsed":"-PT1M","active":"PT0S"},
{"counter":0,"material":[{"id":1781,"uniq":"aaa-0offline-2018-01-28","part":"aaa","proc":2,"numproc":2,"face":"2-1","serial":"00000000sJ","workorder":""}],"type":"CloseOut","startofcycle":false,"endUTC":"2018-01-28T02:04:37.1775022Z","loc":"CloseOut","locnum":1,"pal":0,"program":"","result":"","elapsed":"-PT1M","active":"PT0S"},
{"counter":0,"material":[{"id":1779,"uniq":"zzz-4offline-2018-01-27","part":"zzz","proc":1,"numproc":1,"face":"1-1","serial":"00000000sH","workorder":""}],"type":"CloseOut","startofcycle":false,"endUTC":"2018-01-28T02:26:08.0157016Z","loc":"CloseOut","locnum":1,"pal":0,"program":"","result":"","elapsed":"-PT1M","active":"PT0S"},
{"counter":0,"material":[{"id":1777,"uniq":"ccc-2offline-2018-01-27","part":"ccc","proc":2,"numproc":2,"face":"2-1","serial":"00000000sF","workorder":""}],"type":"CloseOut","startofcycle":false,"endUTC":"2018-01-28T02:29:06.3106891Z","loc":"CloseOut","locnum":1,"pal":0,"program":"","result":"","elapsed":"-PT1M","active":"PT0S"},
{"counter":0,"material":[{"id":1782,"uniq":"aaa-0offline-2018-01-28","part":"aaa","proc":2,"numproc":2,"face":"2-1","serial":"00000000sK","workorder":""}],"type":"CloseOut","startofcycle":false,"endUTC":"2018-01-28T03:04:43.5632274Z","loc":"CloseOut","locnum":1,"pal":0,"program":"","result":"","elapsed":"-PT1M","active":"PT0S"},
{"counter":0,"material":[{"id":1783,"uniq":"xxx-3offline-2018-01-28","part":"xxx","proc":1,"numproc":1,"face":"1-1","serial":"00000000sL","workorder":""}],"type":"CloseOut","startofcycle":false,"endUTC":"2018-01-28T03:21:30.1901395Z","loc":"CloseOut","locnum":1,"pal":0,"program":"","result":"","elapsed":"-PT1M","active":"PT0S"},
{"counter":0,"material":[{"id":1785,"uniq":"aaa-0offline-2018-01-28","part":"aaa","proc":2,"numproc":2,"face":"2-1","serial":"00000000sN","workorder":""}],"type":"CloseOut","startofcycle":false,"endUTC":"2018-01-28T03:48:26.3271795Z","loc":"CloseOut","locnum":1,"pal":0,"program":"","result":"","elapsed":"-PT1M","active":"PT0S"},
{"counter":0,"material":[{"id":1784,"uniq":"zzz-4offline-2018-01-28","part":"zzz","proc":1,"numproc":1,"face":"1-1","serial":"00000000sM","workorder":""}],"type":"CloseOut","startofcycle":false,"endUTC":"2018-01-28T04:10:13.2162955Z","loc":"CloseOut","locnum":1,"pal":0,"program":"","result":"","elapsed":"-PT1M","active":"PT0S"},
{"counter":0,"material":[{"id":1778,"uniq":"ccc-2offline-2018-01-27","part":"ccc","proc":2,"numproc":2,"face":"2-1","serial":"00000000sG","workorder":""}],"type":"CloseOut","startofcycle":false,"endUTC":"2018-01-28T04:19:03.701069Z","loc":"CloseOut","locnum":1,"pal":0,"program":"","result":"","elapsed":"-PT1M","active":"PT0S"},
{"counter":0,"material":[{"id":1787,"uniq":"aaa-0offline-2018-01-28","part":"aaa","proc":2,"numproc":2,"face":"2-1","serial":"00000000sP","workorder":""}],"type":"CloseOut","startofcycle":false,"endUTC":"2018-01-28T04:21:15.160396Z","loc":"CloseOut","locnum":1,"pal":0,"program":"","result":"","elapsed":"-PT1M","active":"PT0S"},
{"counter":0,"material":[{"id":1790,"uniq":"xxx-3offline-2018-01-28","part":"xxx","proc":1,"numproc":1,"face":"1-1","serial":"00000000sS","workorder":""}],"type":"CloseOut","startofcycle":false,"endUTC":"2018-01-28T04:26:24.0386072Z","loc":"CloseOut","locnum":1,"pal":0,"program":"","result":"","elapsed":"-PT1M","active":"PT0S"},
{"counter":0,"material":[{"id":1788,"uniq":"aaa-0offline-2018-01-28","part":"aaa","proc":2,"numproc":2,"face":"2-1","serial":"00000000sQ","workorder":""}],"type":"CloseOut","startofcycle":false,"endUTC":"2018-01-28T04:54:01.0900112Z","loc":"CloseOut","locnum":1,"pal":0,"program":"","result":"","elapsed":"-PT1M","active":"PT0S"},
{"counter":0,"material":[{"id":1792,"uniq":"xxx-3offline-2018-01-28","part":"xxx","proc":1,"numproc":1,"face":"1-1","serial":"00000000sU","workorder":""}],"type":"CloseOut","startofcycle":false,"endUTC":"2018-01-28T05:28:47.1394733Z","loc":"CloseOut","locnum":1,"pal":0,"program":"","result":"","elapsed":"-PT1M","active":"PT0S"},
{"counter":0,"material":[{"id":1791,"uniq":"bbb-1offline-2018-01-28","part":"bbb","proc":2,"numproc":2,"face":"2-1","serial":"00000000sT","workorder":""}],"type":"CloseOut","startofcycle":false,"endUTC":"2018-01-28T05:44:57.940787Z","loc":"CloseOut","locnum":1,"pal":0,"program":"","result":"","elapsed":"-PT1M","active":"PT0S"},
{"counter":0,"material":[{"id":1780,"uniq":"ccc-2offline-2018-01-27","part":"ccc","proc":2,"numproc":2,"face":"2-1","serial":"00000000sI","workorder":""}],"type":"CloseOut","startofcycle":false,"endUTC":"2018-01-28T06:11:06.161447Z","loc":"CloseOut","locnum":1,"pal":0,"program":"","result":"","elapsed":"-PT1M","active":"PT0S"},
{"counter":0,"material":[{"id":1797,"uniq":"xxx-3offline-2018-01-28","part":"xxx","proc":1,"numproc":1,"face":"1-1","serial":"00000000sZ","workorder":""}],"type":"CloseOut","startofcycle":false,"endUTC":"2018-01-28T06:24:29.7692839Z","loc":"CloseOut","locnum":1,"pal":0,"program":"","result":"","elapsed":"-PT1M","active":"PT0S"},
{"counter":0,"material":[{"id":1793,"uniq":"bbb-1offline-2018-01-28","part":"bbb","proc":2,"numproc":2,"face":"2-1","serial":"00000000sV","workorder":""}],"type":"CloseOut","startofcycle":false,"endUTC":"2018-01-28T06:30:26.5179158Z","loc":"CloseOut","locnum":1,"pal":0,"program":"","result":"","elapsed":"-PT1M","active":"PT0S"},
{"counter":0,"material":[{"id":1796,"uniq":"bbb-1offline-2018-01-28","part":"bbb","proc":2,"numproc":2,"face":"2-1","serial":"00000000sY","workorder":""}],"type":"CloseOut","startofcycle":false,"endUTC":"2018-01-28T07:17:46.195579Z","loc":"CloseOut","locnum":1,"pal":0,"program":"","result":"","elapsed":"-PT1M","active":"PT0S"},
{"counter":0,"material":[{"id":1799,"uniq":"xxx-3offline-2018-01-28","part":"xxx","proc":1,"numproc":1,"face":"1-1","serial":"00000000t1","workorder":""}],"type":"CloseOut","startofcycle":false,"endUTC":"2018-01-28T07:19:16.4146449Z","loc":"CloseOut","locnum":1,"pal":0,"program":"","result":"","elapsed":"-PT1M","active":"PT0S"},
{"counter":0,"material":[{"id":1794,"uniq":"zzz-4offline-2018-01-28","part":"zzz","proc":1,"numproc":1,"face":"1-1","serial":"00000000sW","workorder":""}],"type":"CloseOut","startofcycle":false,"endUTC":"2018-01-28T07:34:30.9618074Z","loc":"CloseOut","locnum":1,"pal":0,"program":"","result":"","elapsed":"-PT1M","active":"PT0S"},
{"counter":0,"material":[{"id":1798,"uniq":"bbb-1offline-2018-01-28","part":"bbb","proc":2,"numproc":2,"face":"2-1","serial":"00000000t0","workorder":""}],"type":"CloseOut","startofcycle":false,"endUTC":"2018-01-28T08:07:41.7658468Z","loc":"CloseOut","locnum":1,"pal":0,"program":"","result":"","elapsed":"-PT1M","active":"PT0S"},
{"counter":0,"material":[{"id":1802,"uniq":"xxx-3offline-2018-01-28","part":"xxx","proc":1,"numproc":1,"face":"1-1","serial":"00000000t4","workorder":""}],"type":"CloseOut","startofcycle":false,"endUTC":"2018-01-28T08:14:45.605574Z","loc":"CloseOut","locnum":1,"pal":0,"program":"","result":"","elapsed":"-PT1M","active":"PT0S"},
{"counter":0,"material":[{"id":1789,"uniq":"ccc-2offline-2018-01-27","part":"ccc","proc":2,"numproc":2,"face":"2-1","serial":"00000000sR","workorder":""}],"type":"CloseOut","startofcycle":false,"endUTC":"2018-01-28T08:16:09.1036637Z","loc":"CloseOut","locnum":1,"pal":0,"program":"","result":"","elapsed":"-PT1M","active":"PT0S"},
{"counter":0,"material":[{"id":1800,"uniq":"bbb-1offline-2018-01-28","part":"bbb","proc":2,"numproc":2,"face":"2-1","serial":"00000000t2","workorder":""}],"type":"CloseOut","startofcycle":false,"endUTC":"2018-01-28T08:54:08.3605747Z","loc":"CloseOut","locnum":1,"pal":0,"program":"","result":"","elapsed":"-PT1M","active":"PT0S"},
{"counter":0,"material":[{"id":1805,"uniq":"xxx-3offline-2018-01-28","part":"xxx","proc":1,"numproc":1,"face":"1-1","serial":"00000000t7","workorder":""}],"type":"CloseOut","startofcycle":false,"endUTC":"2018-01-28T09:08:35.3179755Z","loc":"CloseOut","locnum":1,"pal":0,"program":"","result":"","elapsed":"-PT1M","active":"PT0S"},
{"counter":0,"material":[{"id":1786,"uniq":"ccc-2offline-2018-01-27","part":"ccc","proc":2,"numproc":2,"face":"2-1","serial":"00000000sO","workorder":""}],"type":"CloseOut","startofcycle":false,"endUTC":"2018-01-28T09:30:16.6037133Z","loc":"CloseOut","locnum":1,"pal":0,"program":"","result":"","elapsed":"-PT1M","active":"PT0S"},
{"counter":0,"material":[{"id":1803,"uniq":"bbb-1offline-2018-01-28","part":"bbb","proc":2,"numproc":2,"face":"2-1","serial":"00000000t5","workorder":""}],"type":"CloseOut","startofcycle":false,"endUTC":"2018-01-28T09:42:29.7619367Z","loc":"CloseOut","locnum":1,"pal":0,"program":"","result":"","elapsed":"-PT1M","active":"PT0S"},
{"counter":0,"material":[{"id":1809,"uniq":"xxx-3offline-2018-01-28","part":"xxx","proc":1,"numproc":1,"face":"1-1","serial":"00000000tb","workorder":""}],"type":"CloseOut","startofcycle":false,"endUTC":"2018-01-28T10:04:21.0339989Z","loc":"CloseOut","locnum":1,"pal":0,"program":"","result":"","elapsed":"-PT1M","active":"PT0S"},
{"counter":0,"material":[{"id":1801,"uniq":"ccc-2offline-2018-01-27","part":"ccc","proc":2,"numproc":2,"face":"2-1","serial":"00000000t3","workorder":""}],"type":"CloseOut","startofcycle":false,"endUTC":"2018-01-28T10:31:16.8311615Z","loc":"CloseOut","locnum":1,"pal":0,"program":"","result":"","elapsed":"-PT1M","active":"PT0S"},
{"counter":0,"material":[{"id":1804,"uniq":"bbb-1offline-2018-01-28","part":"bbb","proc":2,"numproc":2,"face":"2-1","serial":"00000000t6","workorder":""}],"type":"CloseOut","startofcycle":false,"endUTC":"2018-01-28T10:44:22.4706635Z","loc":"CloseOut","locnum":1,"pal":0,"program":"","result":"","elapsed":"-PT1M","active":"PT0S"},
{"counter":0,"material":[{"id":1811,"uniq":"xxx-3offline-2018-01-28","part":"xxx","proc":1,"numproc":1,"face":"1-1","serial":"00000000td","workorder":""}],"type":"CloseOut","startofcycle":false,"endUTC":"2018-01-28T10:59:36.5721675Z","loc":"CloseOut","locnum":1,"pal":0,"program":"","result":"","elapsed":"-PT1M","active":"PT0S"},
{"counter":0,"material":[{"id":1814,"uniq":"xxx-3offline-2018-01-28","part":"xxx","proc":1,"numproc":1,"face":"1-1","serial":"00000000tg","workorder":""}],"type":"CloseOut","startofcycle":false,"endUTC":"2018-01-28T11:32:27.3922309Z","loc":"CloseOut","locnum":1,"pal":0,"program":"","result":"","elapsed":"-PT1M","active":"PT0S"},
{"counter":0,"material":[{"id":1817,"uniq":"xxx-3offline-2018-01-28","part":"xxx","proc":1,"numproc":1,"face":"1-1","serial":"00000000tj","workorder":""}],"type":"CloseOut","startofcycle":false,"endUTC":"2018-01-28T12:00:48.4318927Z","loc":"CloseOut","locnum":1,"pal":0,"program":"","result":"","elapsed":"-PT1M","active":"PT0S"},
{"counter":0,"material":[{"id":1795,"uniq":"ccc-2offline-2018-01-27","part":"ccc","proc":2,"numproc":2,"face":"2-1","serial":"00000000sX","workorder":""}],"type":"CloseOut","startofcycle":false,"endUTC":"2018-01-28T12:22:35.6209577Z","loc":"CloseOut","locnum":1,"pal":0,"program":"","result":"","elapsed":"-PT1M","active":"PT0S"},
{"counter":0,"material":[{"id":1810,"uniq":"bbb-1offline-2018-01-28","part":"bbb","proc":2,"numproc":2,"face":"2-1","serial":"00000000tc","workorder":""}],"type":"CloseOut","startofcycle":false,"endUTC":"2018-01-28T12:26:08.8366773Z","loc":"CloseOut","locnum":1,"pal":0,"program":"","result":"","elapsed":"-PT1M","active":"PT0S"},
{"counter":0,"material":[{"id":1806,"uniq":"zzz-4offline-2018-01-28","part":"zzz","proc":1,"numproc":1,"face":"1-1","serial":"00000000t8","workorder":""}],"type":"CloseOut","startofcycle":false,"endUTC":"2018-01-28T12:40:45.797921Z","loc":"CloseOut","locnum":1,"pal":0,"program":"","result":"","elapsed":"-PT1M","active":"PT0S"},
{"counter":0,"material":[{"id":1819,"uniq":"xxx-3offline-2018-01-28","part":"xxx","proc":1,"numproc":1,"face":"1-1","serial":"00000000tl","workorder":""}],"type":"CloseOut","startofcycle":false,"endUTC":"2018-01-28T13:02:43.7234216Z","loc":"CloseOut","locnum":1,"pal":0,"program":"","result":"","elapsed":"-PT1M","active":"PT0S"},
{"counter":0,"material":[{"id":1818,"uniq":"xxx-3offline-2018-01-28","part":"xxx","proc":1,"numproc":1,"face":"1-1","serial":"00000000tk","workorder":""}],"type":"CloseOut","startofcycle":false,"endUTC":"2018-01-28T13:15:27.6886253Z","loc":"CloseOut","locnum":1,"pal":0,"program":"","result":"","elapsed":"-PT1M","active":"PT0S"},
{"counter":0,"material":[{"id":1807,"uniq":"bbb-1offline-2018-01-28","part":"bbb","proc":2,"numproc":2,"face":"2-1","serial":"00000000t9","workorder":""}],"type":"CloseOut","startofcycle":false,"endUTC":"2018-01-28T13:35:13.5154213Z","loc":"CloseOut","locnum":1,"pal":0,"program":"","result":"","elapsed":"-PT1M","active":"PT0S"},
{"counter":0,"material":[{"id":1816,"uniq":"bbb-1offline-2018-01-28","part":"bbb","proc":2,"numproc":2,"face":"2-1","serial":"00000000ti","workorder":""}],"type":"CloseOut","startofcycle":false,"endUTC":"2018-01-28T14:09:55.005464Z","loc":"CloseOut","locnum":1,"pal":0,"program":"","result":"","elapsed":"-PT1M","active":"PT0S"},
{"counter":0,"material":[{"id":1808,"uniq":"ccc-2offline-2018-01-27","part":"ccc","proc":2,"numproc":2,"face":"2-1","serial":"00000000ta","workorder":""}],"type":"CloseOut","startofcycle":false,"endUTC":"2018-01-28T14:12:28.9993473Z","loc":"CloseOut","locnum":1,"pal":0,"program":"","result":"","elapsed":"-PT1M","active":"PT0S"},
{"counter":0,"material":[{"id":1813,"uniq":"bbb-1offline-2018-01-28","part":"bbb","proc":2,"numproc":2,"face":"2-1","serial":"00000000tf","workorder":""}],"type":"CloseOut","startofcycle":false,"endUTC":"2018-01-28T14:36:07.3957257Z","loc":"CloseOut","locnum":1,"pal":0,"program":"","result":"","elapsed":"-PT1M","active":"PT0S"},
{"counter":0,"material":[{"id":1824,"uniq":"xxx-3offline-2018-01-28","part":"xxx","proc":1,"numproc":1,"face":"1-1","serial":"00000000tq","workorder":""}],"type":"CloseOut","startofcycle":false,"endUTC":"2018-01-28T14:57:27.096618Z","loc":"CloseOut","locnum":1,"pal":0,"program":"","result":"","elapsed":"-PT1M","active":"PT0S"},
{"counter":0,"material":[{"id":1821,"uniq":"bbb-1offline-2018-01-28","part":"bbb","proc":2,"numproc":2,"face":"2-1","serial":"00000000tn","workorder":""}],"type":"CloseOut","startofcycle":false,"endUTC":"2018-01-28T15:52:20.0486171Z","loc":"CloseOut","locnum":1,"pal":0,"program":"","result":"","elapsed":"-PT1M","active":"PT0S"},
{"counter":0,"material":[{"id":1822,"uniq":"zzz-4offline-2018-01-28","part":"zzz","proc":1,"numproc":1,"face":"1-1","serial":"00000000to","workorder":""}],"type":"CloseOut","startofcycle":false,"endUTC":"2018-01-28T16:20:06.2577269Z","loc":"CloseOut","locnum":1,"pal":0,"program":"","result":"","elapsed":"-PT1M","active":"PT0S"},
{"counter":0,"material":[{"id":1812,"uniq":"ccc-2offline-2018-01-28","part":"ccc","proc":2,"numproc":2,"face":"2-1","serial":"00000000te","workorder":""}],"type":"CloseOut","startofcycle":false,"endUTC":"2018-01-28T16:20:59.8225028Z","loc":"CloseOut","locnum":1,"pal":0,"program":"","result":"","elapsed":"-PT1M","active":"PT0S"},
{"counter":0,"material":[{"id":1815,"uniq":"ccc-2offline-2018-01-28","part":"ccc","proc":2,"numproc":2,"face":"2-1","serial":"00000000th","workorder":""}],"type":"CloseOut","startofcycle":false,"endUTC":"2018-01-28T16:33:55.1296596Z","loc":"CloseOut","locnum":1,"pal":0,"program":"","result":"","elapsed":"-PT1M","active":"PT0S"},
{"counter":0,"material":[{"id":1829,"uniq":"xxx-3offline-2018-01-28","part":"xxx","proc":1,"numproc":1,"face":"1-1","serial":"00000000tv","workorder":""}],"type":"CloseOut","startofcycle":false,"endUTC":"2018-01-28T16:41:10.4386912Z","loc":"CloseOut","locnum":1,"pal":0,"program":"","result":"","elapsed":"-PT1M","active":"PT0S"},
{"counter":0,"material":[{"id":1823,"uniq":"xxx-3offline-2018-01-28","part":"xxx","proc":1,"numproc":1,"face":"1-1","serial":"00000000tp","workorder":""}],"type":"CloseOut","startofcycle":false,"endUTC":"2018-01-28T17:14:27.8226858Z","loc":"CloseOut","locnum":1,"pal":0,"program":"","result":"","elapsed":"-PT1M","active":"PT0S"},
{"counter":0,"material":[{"id":1825,"uniq":"bbb-1offline-2018-01-28","part":"bbb","proc":2,"numproc":2,"face":"2-1","serial":"00000000tr","workorder":""}],"type":"CloseOut","startofcycle":false,"endUTC":"2018-01-28T17:15:59.6640531Z","loc":"CloseOut","locnum":1,"pal":0,"program":"","result":"","elapsed":"-PT1M","active":"PT0S"},
{"counter":0,"material":[{"id":1826,"uniq":"bbb-1offline-2018-01-28","part":"bbb","proc":2,"numproc":2,"face":"2-1","serial":"00000000ts","workorder":""}],"type":"CloseOut","startofcycle":false,"endUTC":"2018-01-28T17:35:25.2066445Z","loc":"CloseOut","locnum":1,"pal":0,"program":"","result":"","elapsed":"-PT1M","active":"PT0S"},
{"counter":0,"material":[{"id":1836,"uniq":"xxx-3offline-2018-01-28","part":"xxx","proc":1,"numproc":1,"face":"1-1","serial":"00000000tC","workorder":""}],"type":"CloseOut","startofcycle":false,"endUTC":"2018-01-28T18:15:03.8024324Z","loc":"CloseOut","locnum":1,"pal":0,"program":"","result":"","elapsed":"-PT1M","active":"PT0S"},
{"counter":0,"material":[{"id":1834,"uniq":"xxx-3offline-2018-01-28","part":"xxx","proc":1,"numproc":1,"face":"1-1","serial":"00000000tA","workorder":""}],"type":"CloseOut","startofcycle":false,"endUTC":"2018-01-28T18:24:34.1817451Z","loc":"CloseOut","locnum":1,"pal":0,"program":"","result":"","elapsed":"-PT1M","active":"PT0S"},
{"counter":0,"material":[{"id":1820,"uniq":"ccc-2offline-2018-01-28","part":"ccc","proc":2,"numproc":2,"face":"2-1","serial":"00000000tm","workorder":""}],"type":"CloseOut","startofcycle":false,"endUTC":"2018-01-28T18:24:41.5110036Z","loc":"CloseOut","locnum":1,"pal":0,"program":"","result":"","elapsed":"-PT1M","active":"PT0S"},
{"counter":0,"material":[{"id":1838,"uniq":"xxx-3offline-2018-01-28","part":"xxx","proc":1,"numproc":1,"face":"1-1","serial":"00000000tE","workorder":""}],"type":"CloseOut","startofcycle":false,"endUTC":"2018-01-28T19:17:08.773868Z","loc":"CloseOut","locnum":1,"pal":0,"program":"","result":"","elapsed":"-PT1M","active":"PT0S"},
{"counter":0,"material":[{"id":1830,"uniq":"bbb-1offline-2018-01-28","part":"bbb","proc":2,"numproc":2,"face":"2-1","serial":"00000000tw","workorder":""}],"type":"CloseOut","startofcycle":false,"endUTC":"2018-01-28T19:17:33.2566918Z","loc":"CloseOut","locnum":1,"pal":0,"program":"","result":"","elapsed":"-PT1M","active":"PT0S"},
{"counter":0,"material":[{"id":1840,"uniq":"xxx-3offline-2018-01-28","part":"xxx","proc":1,"numproc":1,"face":"1-1","serial":"00000000tG","workorder":""}],"type":"CloseOut","startofcycle":false,"endUTC":"2018-01-28T20:12:05.1561346Z","loc":"CloseOut","locnum":1,"pal":0,"program":"","result":"","elapsed":"-PT1M","active":"PT0S"},
{"counter":0,"material":[{"id":1827,"uniq":"ccc-2offline-2018-01-28","part":"ccc","proc":2,"numproc":2,"face":"2-1","serial":"00000000tt","workorder":""}],"type":"CloseOut","startofcycle":false,"endUTC":"2018-01-28T20:14:49.0542786Z","loc":"CloseOut","locnum":1,"pal":0,"program":"","result":"","elapsed":"-PT1M","active":"PT0S"},
{"counter":0,"material":[{"id":1842,"uniq":"xxx-3offline-2018-01-28","part":"xxx","proc":1,"numproc":1,"face":"1-1","serial":"00000000tI","workorder":""}],"type":"CloseOut","startofcycle":false,"endUTC":"2018-01-28T20:16:38.6165107Z","loc":"CloseOut","locnum":1,"pal":0,"program":"","result":"","elapsed":"-PT1M","active":"PT0S"},
{"counter":0,"material":[{"id":1832,"uniq":"zzz-4offline-2018-01-28","part":"zzz","proc":1,"numproc":1,"face":"1-1","serial":"00000000ty","workorder":""}],"type":"CloseOut","startofcycle":false,"endUTC":"2018-01-28T20:40:13.0368987Z","loc":"CloseOut","locnum":1,"pal":0,"program":"","result":"","elapsed":"-PT1M","active":"PT0S"},
{"counter":0,"material":[{"id":1837,"uniq":"bbb-1offline-2018-01-28","part":"bbb","proc":2,"numproc":2,"face":"2-1","serial":"00000000tD","workorder":""}],"type":"CloseOut","startofcycle":false,"endUTC":"2018-01-28T21:10:35.783477Z","loc":"CloseOut","locnum":1,"pal":0,"program":"","result":"","elapsed":"-PT1M","active":"PT0S"},
{"counter":0,"material":[{"id":1828,"uniq":"bbb-1offline-2018-01-28","part":"bbb","proc":2,"numproc":2,"face":"2-1","serial":"00000000tu","workorder":""}],"type":"CloseOut","startofcycle":false,"endUTC":"2018-01-28T21:34:22.6533856Z","loc":"CloseOut","locnum":1,"pal":0,"program":"","result":"","elapsed":"-PT1M","active":"PT0S"},
{"counter":0,"material":[{"id":1831,"uniq":"ccc-2offline-2018-01-28","part":"ccc","proc":2,"numproc":2,"face":"2-1","serial":"00000000tx","workorder":""}],"type":"CloseOut","startofcycle":false,"endUTC":"2018-01-28T22:06:22.0178524Z","loc":"CloseOut","locnum":1,"pal":0,"program":"","result":"","elapsed":"-PT1M","active":"PT0S"},
{"counter":0,"material":[{"id":1841,"uniq":"bbb-1offline-2018-01-28","part":"bbb","proc":2,"numproc":2,"face":"2-1","serial":"00000000tH","workorder":""}],"type":"CloseOut","startofcycle":false,"endUTC":"2018-01-28T22:07:36.1629383Z","loc":"CloseOut","locnum":1,"pal":0,"program":"","result":"","elapsed":"-PT1M","active":"PT0S"},
{"counter":0,"material":[{"id":1835,"uniq":"bbb-1offline-2018-01-28","part":"bbb","proc":2,"numproc":2,"face":"2-1","serial":"00000000tB","workorder":""}],"type":"CloseOut","startofcycle":false,"endUTC":"2018-01-28T22:18:49.3484213Z","loc":"CloseOut","locnum":1,"pal":0,"program":"","result":"","elapsed":"-PT1M","active":"PT0S"},
{"counter":0,"material":[{"id":1845,"uniq":"bbb-1offline-2018-01-28","part":"bbb","proc":2,"numproc":2,"face":"2-1","serial":"00000000tL","workorder":""}],"type":"CloseOut","startofcycle":false,"endUTC":"2018-01-28T22:52:12.5141526Z","loc":"CloseOut","locnum":1,"pal":0,"program":"","result":"","elapsed":"-PT1M","active":"PT0S"},
{"counter":0,"material":[{"id":1850,"uniq":"xxx-3offline-2018-01-29","part":"xxx","proc":1,"numproc":1,"face":"1-1","serial":"00000000tQ","workorder":""}],"type":"CloseOut","startofcycle":false,"endUTC":"2018-01-29T01:31:31.347989Z","loc":"CloseOut","locnum":1,"pal":0,"program":"","result":"","elapsed":"-PT1M","active":"PT0S"},
{"counter":0,"material":[{"id":1839,"uniq":"ccc-2offline-2018-01-28","part":"ccc","proc":2,"numproc":2,"face":"2-1","serial":"00000000tF","workorder":""}],"type":"CloseOut","startofcycle":false,"endUTC":"2018-01-29T01:46:53.9984007Z","loc":"CloseOut","locnum":1,"pal":0,"program":"","result":"","elapsed":"-PT1M","active":"PT0S"},
{"counter":0,"material":[{"id":1843,"uniq":"ccc-2offline-2018-01-28","part":"ccc","proc":2,"numproc":2,"face":"2-1","serial":"00000000tJ","workorder":""}],"type":"CloseOut","startofcycle":false,"endUTC":"2018-01-29T02:03:06.9011181Z","loc":"CloseOut","locnum":1,"pal":0,"program":"","result":"","elapsed":"-PT1M","active":"PT0S"},
{"counter":0,"material":[{"id":1851,"uniq":"xxx-3offline-2018-01-29","part":"xxx","proc":1,"numproc":1,"face":"1-1","serial":"00000000tR","workorder":""}],"type":"CloseOut","startofcycle":false,"endUTC":"2018-01-29T02:28:16.4662834Z","loc":"CloseOut","locnum":1,"pal":0,"program":"","result":"","elapsed":"-PT1M","active":"PT0S"},
{"counter":0,"material":[{"id":1854,"uniq":"xxx-3offline-2018-01-29","part":"xxx","proc":1,"numproc":1,"face":"1-1","serial":"00000000tU","workorder":""}],"type":"CloseOut","startofcycle":false,"endUTC":"2018-01-29T03:23:06.3362252Z","loc":"CloseOut","locnum":1,"pal":0,"program":"","result":"","elapsed":"-PT1M","active":"PT0S"},
{"counter":0,"material":[{"id":1852,"uniq":"zzz-4offline-2018-01-29","part":"zzz","proc":1,"numproc":1,"face":"1-1","serial":"00000000tS","workorder":""}],"type":"CloseOut","startofcycle":false,"endUTC":"2018-01-29T03:38:39.6943952Z","loc":"CloseOut","locnum":1,"pal":0,"program":"","result":"","elapsed":"-PT1M","active":"PT0S"},
{"counter":0,"material":[{"id":1846,"uniq":"ccc-2offline-2018-01-28","part":"ccc","proc":2,"numproc":2,"face":"2-1","serial":"00000000tM","workorder":""}],"type":"CloseOut","startofcycle":false,"endUTC":"2018-01-29T03:49:58.706907Z","loc":"CloseOut","locnum":1,"pal":0,"program":"","result":"","elapsed":"-PT1M","active":"PT0S"},
{"counter":0,"material":[{"id":1847,"uniq":"ccc-2offline-2018-01-28","part":"ccc","proc":2,"numproc":2,"face":"2-1","serial":"00000000tN","workorder":""}],"type":"CloseOut","startofcycle":false,"endUTC":"2018-01-29T04:06:03.7232463Z","loc":"CloseOut","locnum":1,"pal":0,"program":"","result":"","elapsed":"-PT1M","active":"PT0S"},
{"counter":0,"material":[{"id":1858,"uniq":"xxx-3offline-2018-01-29","part":"xxx","proc":1,"numproc":1,"face":"1-1","serial":"00000000tY","workorder":""}],"type":"CloseOut","startofcycle":false,"endUTC":"2018-01-29T04:17:59.8179449Z","loc":"CloseOut","locnum":1,"pal":0,"program":"","result":"","elapsed":"-PT1M","active":"PT0S"},
{"counter":0,"material":[{"id":1848,"uniq":"bbb-1offline-2018-01-29","part":"bbb","proc":2,"numproc":2,"face":"2-1","serial":"00000000tO","workorder":""}],"type":"CloseOut","startofcycle":false,"endUTC":"2018-01-29T04:32:50.3537881Z","loc":"CloseOut","locnum":1,"pal":0,"program":"","result":"","elapsed":"-PT1M","active":"PT0S"},
{"counter":0,"material":[{"id":1849,"uniq":"bbb-1offline-2018-01-29","part":"bbb","proc":2,"numproc":2,"face":"2-1","serial":"00000000tP","workorder":""}],"type":"CloseOut","startofcycle":false,"endUTC":"2018-01-29T04:53:05.2712016Z","loc":"CloseOut","locnum":1,"pal":0,"program":"","result":"","elapsed":"-PT1M","active":"PT0S"},
{"counter":0,"material":[{"id":1855,"uniq":"ccc-2offline-2018-01-28","part":"ccc","proc":2,"numproc":2,"face":"2-1","serial":"00000000tV","workorder":""}],"type":"CloseOut","startofcycle":false,"endUTC":"2018-01-29T05:52:25.2936843Z","loc":"CloseOut","locnum":1,"pal":0,"program":"","result":"","elapsed":"-PT1M","active":"PT0S"},
{"counter":0,"material":[{"id":1863,"uniq":"xxx-3offline-2018-01-29","part":"xxx","proc":1,"numproc":1,"face":"1-1","serial":"00000000u3","workorder":""}],"type":"CloseOut","startofcycle":false,"endUTC":"2018-01-29T06:05:54.5692783Z","loc":"CloseOut","locnum":1,"pal":0,"program":"","result":"","elapsed":"-PT1M","active":"PT0S"},
{"counter":0,"material":[{"id":1856,"uniq":"ccc-2offline-2018-01-28","part":"ccc","proc":2,"numproc":2,"face":"2-1","serial":"00000000tW","workorder":""}],"type":"CloseOut","startofcycle":false,"endUTC":"2018-01-29T06:46:19.3907407Z","loc":"CloseOut","locnum":1,"pal":0,"program":"","result":"","elapsed":"-PT1M","active":"PT0S"},
{"counter":0,"material":[{"id":1866,"uniq":"xxx-3offline-2018-01-29","part":"xxx","proc":1,"numproc":1,"face":"1-1","serial":"00000000u6","workorder":""}],"type":"CloseOut","startofcycle":false,"endUTC":"2018-01-29T07:00:46.863481Z","loc":"CloseOut","locnum":1,"pal":0,"program":"","result":"","elapsed":"-PT1M","active":"PT0S"},
{"counter":0,"material":[{"id":1857,"uniq":"bbb-1offline-2018-01-29","part":"bbb","proc":2,"numproc":2,"face":"2-1","serial":"00000000tX","workorder":""}],"type":"CloseOut","startofcycle":false,"endUTC":"2018-01-29T07:32:44.9345953Z","loc":"CloseOut","locnum":1,"pal":0,"program":"","result":"","elapsed":"-PT1M","active":"PT0S"},
{"counter":0,"material":[{"id":1860,"uniq":"zzz-4offline-2018-01-29","part":"zzz","proc":1,"numproc":1,"face":"1-1","serial":"00000000u0","workorder":""}],"type":"CloseOut","startofcycle":false,"endUTC":"2018-01-29T07:43:20.2170175Z","loc":"CloseOut","locnum":1,"pal":0,"program":"","result":"","elapsed":"-PT1M","active":"PT0S"},
{"counter":0,"material":[{"id":1861,"uniq":"ccc-2offline-2018-01-28","part":"ccc","proc":2,"numproc":2,"face":"2-1","serial":"00000000u1","workorder":""}],"type":"CloseOut","startofcycle":false,"endUTC":"2018-01-29T07:55:00.257291Z","loc":"CloseOut","locnum":1,"pal":0,"program":"","result":"","elapsed":"-PT1M","active":"PT0S"},
{"counter":0,"material":[{"id":1868,"uniq":"xxx-3offline-2018-01-29","part":"xxx","proc":1,"numproc":1,"face":"1-1","serial":"00000000u8","workorder":""}],"type":"CloseOut","startofcycle":false,"endUTC":"2018-01-29T07:55:14.6692064Z","loc":"CloseOut","locnum":1,"pal":0,"program":"","result":"","elapsed":"-PT1M","active":"PT0S"},
{"counter":0,"material":[{"id":1865,"uniq":"bbb-1offline-2018-01-29","part":"bbb","proc":2,"numproc":2,"face":"2-1","serial":"00000000u5","workorder":""}],"type":"CloseOut","startofcycle":false,"endUTC":"2018-01-29T08:33:01.8163953Z","loc":"CloseOut","locnum":1,"pal":0,"program":"","result":"","elapsed":"-PT1M","active":"PT0S"},
{"counter":0,"material":[{"id":1853,"uniq":"bbb-1offline-2018-01-29","part":"bbb","proc":2,"numproc":2,"face":"2-1","serial":"00000000tT","workorder":""}],"type":"CloseOut","startofcycle":false,"endUTC":"2018-01-29T08:38:03.2422948Z","loc":"CloseOut","locnum":1,"pal":0,"program":"","result":"","elapsed":"-PT1M","active":"PT0S"},
{"counter":0,"material":[{"id":1870,"uniq":"xxx-3offline-2018-01-29","part":"xxx","proc":1,"numproc":1,"face":"1-1","serial":"00000000ua","workorder":""}],"type":"CloseOut","startofcycle":false,"endUTC":"2018-01-29T08:49:29.8556833Z","loc":"CloseOut","locnum":1,"pal":0,"program":"","result":"","elapsed":"-PT1M","active":"PT0S"},
{"counter":0,"material":[{"id":1871,"uniq":"bbb-1offline-2018-01-29","part":"bbb","proc":2,"numproc":2,"face":"2-1","serial":"00000000ub","workorder":""}],"type":"CloseOut","startofcycle":false,"endUTC":"2018-01-29T09:31:56.8442802Z","loc":"CloseOut","locnum":1,"pal":0,"program":"","result":"","elapsed":"-PT1M","active":"PT0S"},
{"counter":0,"material":[{"id":1874,"uniq":"xxx-3offline-2018-01-29","part":"xxx","proc":1,"numproc":1,"face":"1-1","serial":"00000000ue","workorder":""}],"type":"CloseOut","startofcycle":false,"endUTC":"2018-01-29T09:42:42.1131797Z","loc":"CloseOut","locnum":1,"pal":0,"program":"","result":"","elapsed":"-PT1M","active":"PT0S"},
{"counter":0,"material":[{"id":1862,"uniq":"ccc-2offline-2018-01-28","part":"ccc","proc":2,"numproc":2,"face":"2-1","serial":"00000000u2","workorder":""}],"type":"CloseOut","startofcycle":false,"endUTC":"2018-01-29T09:49:20.7896223Z","loc":"CloseOut","locnum":1,"pal":0,"program":"","result":"","elapsed":"-PT1M","active":"PT0S"},
{"counter":0,"material":[{"id":1864,"uniq":"bbb-1offline-2018-01-29","part":"bbb","proc":2,"numproc":2,"face":"2-1","serial":"00000000u4","workorder":""}],"type":"CloseOut","startofcycle":false,"endUTC":"2018-01-29T10:18:44.9433325Z","loc":"CloseOut","locnum":1,"pal":0,"program":"","result":"","elapsed":"-PT1M","active":"PT0S"},
{"counter":0,"material":[{"id":1877,"uniq":"xxx-3offline-2018-01-29","part":"xxx","proc":1,"numproc":1,"face":"1-1","serial":"00000000uh","workorder":""}],"type":"CloseOut","startofcycle":false,"endUTC":"2018-01-29T10:39:28.0360549Z","loc":"CloseOut","locnum":1,"pal":0,"program":"","result":"","elapsed":"-PT1M","active":"PT0S"},
{"counter":0,"material":[{"id":1880,"uniq":"xxx-3offline-2018-01-29","part":"xxx","proc":1,"numproc":1,"face":"1-1","serial":"00000000uk","workorder":""}],"type":"CloseOut","startofcycle":false,"endUTC":"2018-01-29T11:11:45.4662184Z","loc":"CloseOut","locnum":1,"pal":0,"program":"","result":"","elapsed":"-PT1M","active":"PT0S"},
{"counter":0,"material":[{"id":1867,"uniq":"ccc-2offline-2018-01-28","part":"ccc","proc":2,"numproc":2,"face":"2-1","serial":"00000000u7","workorder":""}],"type":"CloseOut","startofcycle":false,"endUTC":"2018-01-29T11:39:22.697572Z","loc":"CloseOut","locnum":1,"pal":0,"program":"","result":"","elapsed":"-PT1M","active":"PT0S"},
{"counter":0,"material":[{"id":1882,"uniq":"xxx-3offline-2018-01-29","part":"xxx","proc":1,"numproc":1,"face":"1-1","serial":"00000000um","workorder":""}],"type":"CloseOut","startofcycle":false,"endUTC":"2018-01-29T11:40:07.5568623Z","loc":"CloseOut","locnum":1,"pal":0,"program":"","result":"","elapsed":"-PT1M","active":"PT0S"},
{"counter":0,"material":[{"id":1872,"uniq":"zzz-4offline-2018-01-29","part":"zzz","proc":1,"numproc":1,"face":"1-1","serial":"00000000uc","workorder":""}],"type":"CloseOut","startofcycle":false,"endUTC":"2018-01-29T11:47:53.3808246Z","loc":"CloseOut","locnum":1,"pal":0,"program":"","result":"","elapsed":"-PT1M","active":"PT0S"},
{"counter":0,"material":[{"id":1876,"uniq":"bbb-1offline-2018-01-29","part":"bbb","proc":2,"numproc":2,"face":"2-1","serial":"00000000ug","workorder":""}],"type":"CloseOut","startofcycle":false,"endUTC":"2018-01-29T12:28:09.8143237Z","loc":"CloseOut","locnum":1,"pal":0,"program":"","result":"","elapsed":"-PT1M","active":"PT0S"},
{"counter":0,"material":[{"id":1875,"uniq":"bbb-1offline-2018-01-29","part":"bbb","proc":2,"numproc":2,"face":"2-1","serial":"00000000uf","workorder":""}],"type":"CloseOut","startofcycle":false,"endUTC":"2018-01-29T12:37:45.1336002Z","loc":"CloseOut","locnum":1,"pal":0,"program":"","result":"","elapsed":"-PT1M","active":"PT0S"},
{"counter":0,"material":[{"id":1885,"uniq":"xxx-3offline-2018-01-29","part":"xxx","proc":1,"numproc":1,"face":"1-1","serial":"00000000up","workorder":""}],"type":"CloseOut","startofcycle":false,"endUTC":"2018-01-29T12:42:36.0911344Z","loc":"CloseOut","locnum":1,"pal":0,"program":"","result":"","elapsed":"-PT1M","active":"PT0S"},
{"counter":0,"material":[{"id":1883,"uniq":"xxx-3offline-2018-01-29","part":"xxx","proc":1,"numproc":1,"face":"1-1","serial":"00000000un","workorder":""}],"type":"CloseOut","startofcycle":false,"endUTC":"2018-01-29T13:16:19.2333859Z","loc":"CloseOut","locnum":1,"pal":0,"program":"","result":"","elapsed":"-PT1M","active":"PT0S"},
{"counter":0,"material":[{"id":1869,"uniq":"ccc-2offline-2018-01-28","part":"ccc","proc":2,"numproc":2,"face":"2-1","serial":"00000000u9","workorder":""}],"type":"CloseOut","startofcycle":false,"endUTC":"2018-01-29T13:31:12.3729935Z","loc":"CloseOut","locnum":1,"pal":0,"program":"","result":"","elapsed":"-PT1M","active":"PT0S"},
{"counter":0,"material":[{"id":1878,"uniq":"bbb-1offline-2018-01-29","part":"bbb","proc":2,"numproc":2,"face":"2-1","serial":"00000000ui","workorder":""}],"type":"CloseOut","startofcycle":false,"endUTC":"2018-01-29T14:17:15.0412168Z","loc":"CloseOut","locnum":1,"pal":0,"program":"","result":"","elapsed":"-PT1M","active":"PT0S"},
{"counter":0,"material":[{"id":1873,"uniq":"ccc-2offline-2018-01-28","part":"ccc","proc":2,"numproc":2,"face":"2-1","serial":"00000000ud","workorder":""}],"type":"CloseOut","startofcycle":false,"endUTC":"2018-01-29T14:29:29.0967396Z","loc":"CloseOut","locnum":1,"pal":0,"program":"","result":"","elapsed":"-PT1M","active":"PT0S"},
{"counter":0,"material":[{"id":1890,"uniq":"xxx-3offline-2018-01-29","part":"xxx","proc":1,"numproc":1,"face":"1-1","serial":"00000000uu","workorder":""}],"type":"CloseOut","startofcycle":false,"endUTC":"2018-01-29T15:04:27.1957557Z","loc":"CloseOut","locnum":1,"pal":0,"program":"","result":"","elapsed":"-PT1M","active":"PT0S"},
{"counter":0,"material":[{"id":1881,"uniq":"bbb-1offline-2018-01-29","part":"bbb","proc":2,"numproc":2,"face":"2-1","serial":"00000000ul","workorder":""}],"type":"CloseOut","startofcycle":false,"endUTC":"2018-01-29T15:18:33.8730282Z","loc":"CloseOut","locnum":1,"pal":0,"program":"","result":"","elapsed":"-PT1M","active":"PT0S"},
{"counter":0,"material":[{"id":1886,"uniq":"zzz-4offline-2018-01-29","part":"zzz","proc":1,"numproc":1,"face":"1-1","serial":"00000000uq","workorder":""}],"type":"CloseOut","startofcycle":false,"endUTC":"2018-01-29T15:59:25.2165119Z","loc":"CloseOut","locnum":1,"pal":0,"program":"","result":"","elapsed":"-PT1M","active":"PT0S"},
{"counter":0,"material":[{"id":1879,"uniq":"bbb-1offline-2018-01-29","part":"bbb","proc":2,"numproc":2,"face":"2-1","serial":"00000000uj","workorder":""}],"type":"CloseOut","startofcycle":false,"endUTC":"2018-01-29T15:59:51.5836562Z","loc":"CloseOut","locnum":1,"pal":0,"program":"","result":"","elapsed":"-PT1M","active":"PT0S"},
{"counter":0,"material":[{"id":1888,"uniq":"bbb-1offline-2018-01-29","part":"bbb","proc":2,"numproc":2,"face":"2-1","serial":"00000000us","workorder":""}],"type":"CloseOut","startofcycle":false,"endUTC":"2018-01-29T16:12:30.09886Z","loc":"CloseOut","locnum":1,"pal":0,"program":"","result":"","elapsed":"-PT1M","active":"PT0S"},
{"counter":0,"material":[{"id":1884,"uniq":"ccc-2offline-2018-01-29","part":"ccc","proc":2,"numproc":2,"face":"2-1","serial":"00000000uo","workorder":""}],"type":"CloseOut","startofcycle":false,"endUTC":"2018-01-29T16:33:19.0238552Z","loc":"CloseOut","locnum":1,"pal":0,"program":"","result":"","elapsed":"-PT1M","active":"PT0S"},
{"counter":0,"material":[{"id":1889,"uniq":"xxx-3offline-2018-01-29","part":"xxx","proc":1,"numproc":1,"face":"1-1","serial":"00000000ut","workorder":""}],"type":"CloseOut","startofcycle":false,"endUTC":"2018-01-29T16:55:08.8830051Z","loc":"CloseOut","locnum":1,"pal":0,"program":"","result":"","elapsed":"-PT1M","active":"PT0S"},
{"counter":0,"material":[{"id":1887,"uniq":"bbb-1offline-2018-01-29","part":"bbb","proc":2,"numproc":2,"face":"2-1","serial":"00000000ur","workorder":""}],"type":"CloseOut","startofcycle":false,"endUTC":"2018-01-29T17:24:14.7234215Z","loc":"CloseOut","locnum":1,"pal":0,"program":"","result":"","elapsed":"-PT1M","active":"PT0S"},
{"counter":0,"material":[{"id":1894,"uniq":"aaa-0offline-2018-01-29","part":"aaa","proc":2,"numproc":2,"face":"2-1","serial":"00000000uy","workorder":""}],"type":"CloseOut","startofcycle":false,"endUTC":"2018-01-29T18:16:21.3597403Z","loc":"CloseOut","locnum":1,"pal":0,"program":"","result":"","elapsed":"-PT1M","active":"PT0S"},
{"counter":0,"material":[{"id":1893,"uniq":"ccc-2offline-2018-01-29","part":"ccc","proc":2,"numproc":2,"face":"2-1","serial":"00000000ux","workorder":""}],"type":"CloseOut","startofcycle":false,"endUTC":"2018-01-29T18:36:41.1197195Z","loc":"CloseOut","locnum":1,"pal":0,"program":"","result":"","elapsed":"-PT1M","active":"PT0S"},
{"counter":0,"material":[{"id":1900,"uniq":"aaa-0offline-2018-01-29","part":"aaa","proc":2,"numproc":2,"face":"2-1","serial":"00000000uE","workorder":""}],"type":"CloseOut","startofcycle":false,"endUTC":"2018-01-29T18:41:53.4075429Z","loc":"CloseOut","locnum":1,"pal":0,"program":"","result":"","elapsed":"-PT1M","active":"PT0S"},
{"counter":0,"material":[{"id":1891,"uniq":"bbb-1offline-2018-01-29","part":"bbb","proc":2,"numproc":2,"face":"2-1","serial":"00000000uv","workorder":""}],"type":"CloseOut","startofcycle":false,"endUTC":"2018-01-29T18:48:06.7102613Z","loc":"CloseOut","locnum":1,"pal":0,"program":"","result":"","elapsed":"-PT1M","active":"PT0S"},
{"counter":0,"material":[{"id":1896,"uniq":"zzz-4offline-2018-01-29","part":"zzz","proc":1,"numproc":1,"face":"1-1","serial":"00000000uA","workorder":""}],"type":"CloseOut","startofcycle":false,"endUTC":"2018-01-29T19:24:47.2945561Z","loc":"CloseOut","locnum":1,"pal":0,"program":"","result":"","elapsed":"-PT1M","active":"PT0S"},
{"counter":0,"material":[{"id":1892,"uniq":"bbb-1offline-2018-01-29","part":"bbb","proc":2,"numproc":2,"face":"2-1","serial":"00000000uw","workorder":""}],"type":"CloseOut","startofcycle":false,"endUTC":"2018-01-29T20:30:58.1771113Z","loc":"CloseOut","locnum":1,"pal":0,"program":"","result":"","elapsed":"-PT1M","active":"PT0S"},
{"counter":0,"material":[{"id":1898,"uniq":"ccc-2offline-2018-01-29","part":"ccc","proc":2,"numproc":2,"face":"2-1","serial":"00000000uC","workorder":""}],"type":"CloseOut","startofcycle":false,"endUTC":"2018-01-29T20:41:36.2311592Z","loc":"CloseOut","locnum":1,"pal":0,"program":"","result":"","elapsed":"-PT1M","active":"PT0S"},
{"counter":0,"material":[{"id":1897,"uniq":"aaa-0offline-2018-01-29","part":"aaa","proc":2,"numproc":2,"face":"2-1","serial":"00000000uB","workorder":""}],"type":"CloseOut","startofcycle":false,"endUTC":"2018-01-29T20:53:52.6669934Z","loc":"CloseOut","locnum":1,"pal":0,"program":"","result":"","elapsed":"-PT1M","active":"PT0S"},
{"counter":0,"material":[{"id":1899,"uniq":"zzz-4offline-2018-01-29","part":"zzz","proc":1,"numproc":1,"face":"1-1","serial":"00000000uD","workorder":""}],"type":"CloseOut","startofcycle":false,"endUTC":"2018-01-29T21:57:21.073521Z","loc":"CloseOut","locnum":1,"pal":0,"program":"","result":"","elapsed":"-PT1M","active":"PT0S"},
{"counter":0,"material":[{"id":1901,"uniq":"ccc-2offline-2018-01-29","part":"ccc","proc":2,"numproc":2,"face":"2-1","serial":"00000000uF","workorder":""}],"type":"CloseOut","startofcycle":false,"endUTC":"2018-01-29T22:45:44.6802393Z","loc":"CloseOut","locnum":1,"pal":0,"program":"","result":"","elapsed":"-PT1M","active":"PT0S"},
{"counter":0,"material":[{"id":1903,"uniq":"zzz-4offline-2018-01-29","part":"zzz","proc":1,"numproc":1,"face":"1-1","serial":"00000000uH","workorder":""}],"type":"CloseOut","startofcycle":false,"endUTC":"2018-01-29T22:49:43.2339811Z","loc":"CloseOut","locnum":1,"pal":0,"program":"","result":"","elapsed":"-PT1M","active":"PT0S"},
{"counter":0,"material":[{"id":1895,"uniq":"ccc-2offline-2018-01-29","part":"ccc","proc":2,"numproc":2,"face":"2-1","serial":"00000000uz","workorder":""}],"type":"CloseOut","startofcycle":false,"endUTC":"2018-01-29T23:53:50.6861966Z","loc":"CloseOut","locnum":1,"pal":0,"program":"","result":"","elapsed":"-PT1M","active":"PT0S"},
{"counter":0,"material":[{"id":1904,"uniq":"ccc-2offline-2018-01-29","part":"ccc","proc":2,"numproc":2,"face":"2-1","serial":"00000000uI","workorder":""}],"type":"CloseOut","startofcycle":false,"endUTC":"2018-01-30T00:50:15.8007195Z","loc":"CloseOut","locnum":1,"pal":0,"program":"","result":"","elapsed":"-PT1M","active":"PT0S"},
{"counter":0,"material":[{"id":1905,"uniq":"zzz-4offline-2018-01-29","part":"zzz","proc":1,"numproc":1,"face":"1-1","serial":"00000000uJ","workorder":""}],"type":"CloseOut","startofcycle":false,"endUTC":"2018-01-30T01:20:38.2426639Z","loc":"CloseOut","locnum":1,"pal":0,"program":"","result":"","elapsed":"-PT1M","active":"PT0S"},
{"counter":0,"material":[{"id":1902,"uniq":"ccc-2offline-2018-01-29","part":"ccc","proc":2,"numproc":2,"face":"2-1","serial":"00000000uG","workorder":""}],"type":"CloseOut","startofcycle":false,"endUTC":"2018-01-30T01:56:55.6816545Z","loc":"CloseOut","locnum":1,"pal":0,"program":"","result":"","elapsed":"-PT1M","active":"PT0S"},
{"counter":0,"material":[{"id":1907,"uniq":"zzz-4offline-2018-01-29","part":"zzz","proc":1,"numproc":1,"face":"1-1","serial":"00000000uL","workorder":""}],"type":"CloseOut","startofcycle":false,"endUTC":"2018-01-30T02:17:34.1008174Z","loc":"CloseOut","locnum":1,"pal":0,"program":"","result":"","elapsed":"-PT1M","active":"PT0S"},
{"counter":0,"material":[{"id":1911,"uniq":"xxx-3offline-2018-01-30","part":"xxx","proc":1,"numproc":1,"face":"1-1","serial":"00000000uP","workorder":""}],"type":"CloseOut","startofcycle":false,"endUTC":"2018-01-30T02:39:43.4895082Z","loc":"CloseOut","locnum":1,"pal":0,"program":"","result":"","elapsed":"-PT1M","active":"PT0S"},
{"counter":0,"material":[{"id":1906,"uniq":"ccc-2offline-2018-01-29","part":"ccc","proc":2,"numproc":2,"face":"2-1","serial":"00000000uK","workorder":""}],"type":"CloseOut","startofcycle":false,"endUTC":"2018-01-30T03:15:32.6440788Z","loc":"CloseOut","locnum":1,"pal":0,"program":"","result":"","elapsed":"-PT1M","active":"PT0S"},
{"counter":0,"material":[{"id":1910,"uniq":"aaa-0offline-2018-01-30","part":"aaa","proc":2,"numproc":2,"face":"2-1","serial":"00000000uO","workorder":""}],"type":"CloseOut","startofcycle":false,"endUTC":"2018-01-30T03:29:12.8266987Z","loc":"CloseOut","locnum":1,"pal":0,"program":"","result":"","elapsed":"-PT1M","active":"PT0S"},
{"counter":0,"material":[{"id":1913,"uniq":"xxx-3offline-2018-01-30","part":"xxx","proc":1,"numproc":1,"face":"1-1","serial":"00000000uR","workorder":""}],"type":"CloseOut","startofcycle":false,"endUTC":"2018-01-30T03:35:26.6310063Z","loc":"CloseOut","locnum":1,"pal":0,"program":"","result":"","elapsed":"-PT1M","active":"PT0S"},
{"counter":0,"material":[{"id":1908,"uniq":"ccc-2offline-2018-01-29","part":"ccc","proc":2,"numproc":2,"face":"2-1","serial":"00000000uM","workorder":""}],"type":"CloseOut","startofcycle":false,"endUTC":"2018-01-30T04:01:01.6959662Z","loc":"CloseOut","locnum":1,"pal":0,"program":"","result":"","elapsed":"-PT1M","active":"PT0S"},
{"counter":0,"material":[{"id":1917,"uniq":"xxx-3offline-2018-01-30","part":"xxx","proc":1,"numproc":1,"face":"1-1","serial":"00000000uV","workorder":""}],"type":"CloseOut","startofcycle":false,"endUTC":"2018-01-30T04:20:20.8332793Z","loc":"CloseOut","locnum":1,"pal":0,"program":"","result":"","elapsed":"-PT1M","active":"PT0S"},
{"counter":0,"material":[{"id":1909,"uniq":"aaa-0offline-2018-01-30","part":"aaa","proc":2,"numproc":2,"face":"2-1","serial":"00000000uN","workorder":""}],"type":"CloseOut","startofcycle":false,"endUTC":"2018-01-30T04:21:59.0779711Z","loc":"CloseOut","locnum":1,"pal":0,"program":"","result":"","elapsed":"-PT1M","active":"PT0S"},
{"counter":0,"material":[{"id":1914,"uniq":"aaa-0offline-2018-01-30","part":"aaa","proc":2,"numproc":2,"face":"2-1","serial":"00000000uS","workorder":""}],"type":"CloseOut","startofcycle":false,"endUTC":"2018-01-30T05:09:30.6266207Z","loc":"CloseOut","locnum":1,"pal":0,"program":"","result":"","elapsed":"-PT1M","active":"PT0S"},
{"counter":0,"material":[{"id":1912,"uniq":"ccc-2offline-2018-01-29","part":"ccc","proc":2,"numproc":2,"face":"2-1","serial":"00000000uQ","workorder":""}],"type":"CloseOut","startofcycle":false,"endUTC":"2018-01-30T05:18:03.8818586Z","loc":"CloseOut","locnum":1,"pal":0,"program":"","result":"","elapsed":"-PT1M","active":"PT0S"},
{"counter":0,"material":[{"id":1921,"uniq":"xxx-3offline-2018-01-30","part":"xxx","proc":1,"numproc":1,"face":"1-1","serial":"00000000uZ","workorder":""}],"type":"CloseOut","startofcycle":false,"endUTC":"2018-01-30T05:25:55.8994882Z","loc":"CloseOut","locnum":1,"pal":0,"program":"","result":"","elapsed":"-PT1M","active":"PT0S"},
{"counter":0,"material":[{"id":1918,"uniq":"aaa-0offline-2018-01-30","part":"aaa","proc":2,"numproc":2,"face":"2-1","serial":"00000000uW","workorder":""}],"type":"CloseOut","startofcycle":false,"endUTC":"2018-01-30T05:52:21.181532Z","loc":"CloseOut","locnum":1,"pal":0,"program":"","result":"","elapsed":"-PT1M","active":"PT0S"},
{"counter":0,"material":[{"id":1924,"uniq":"xxx-3offline-2018-01-30","part":"xxx","proc":1,"numproc":1,"face":"1-1","serial":"00000000v2","workorder":""}],"type":"CloseOut","startofcycle":false,"endUTC":"2018-01-30T06:19:36.334412Z","loc":"CloseOut","locnum":1,"pal":0,"program":"","result":"","elapsed":"-PT1M","active":"PT0S"},
{"counter":0,"material":[{"id":1920,"uniq":"aaa-0offline-2018-01-30","part":"aaa","proc":2,"numproc":2,"face":"2-1","serial":"00000000uY","workorder":""}],"type":"CloseOut","startofcycle":false,"endUTC":"2018-01-30T06:30:43.3374577Z","loc":"CloseOut","locnum":1,"pal":0,"program":"","result":"","elapsed":"-PT1M","active":"PT0S"},
{"counter":0,"material":[{"id":1916,"uniq":"zzz-4offline-2018-01-30","part":"zzz","proc":1,"numproc":1,"face":"1-1","serial":"00000000uU","workorder":""}],"type":"CloseOut","startofcycle":false,"endUTC":"2018-01-30T07:11:34.4034457Z","loc":"CloseOut","locnum":1,"pal":0,"program":"","result":"","elapsed":"-PT1M","active":"PT0S"},
{"counter":0,"material":[{"id":1923,"uniq":"aaa-0offline-2018-01-30","part":"aaa","proc":2,"numproc":2,"face":"2-1","serial":"00000000v1","workorder":""}],"type":"CloseOut","startofcycle":false,"endUTC":"2018-01-30T07:17:02.4091293Z","loc":"CloseOut","locnum":1,"pal":0,"program":"","result":"","elapsed":"-PT1M","active":"PT0S"},
{"counter":0,"material":[{"id":1927,"uniq":"xxx-3offline-2018-01-30","part":"xxx","proc":1,"numproc":1,"face":"1-1","serial":"00000000v5","workorder":""}],"type":"CloseOut","startofcycle":false,"endUTC":"2018-01-30T07:23:58.0264894Z","loc":"CloseOut","locnum":1,"pal":0,"program":"","result":"","elapsed":"-PT1M","active":"PT0S"},
{"counter":0,"material":[{"id":1919,"uniq":"ccc-2offline-2018-01-29","part":"ccc","proc":2,"numproc":2,"face":"2-1","serial":"00000000uX","workorder":""}],"type":"CloseOut","startofcycle":false,"endUTC":"2018-01-30T07:24:38.423772Z","loc":"CloseOut","locnum":1,"pal":0,"program":"","result":"","elapsed":"-PT1M","active":"PT0S"},
{"counter":0,"material":[{"id":1925,"uniq":"aaa-0offline-2018-01-30","part":"aaa","proc":2,"numproc":2,"face":"2-1","serial":"00000000v3","workorder":""}],"type":"CloseOut","startofcycle":false,"endUTC":"2018-01-30T07:58:52.6415729Z","loc":"CloseOut","locnum":1,"pal":0,"program":"","result":"","elapsed":"-PT1M","active":"PT0S"},
{"counter":0,"material":[{"id":1929,"uniq":"xxx-3offline-2018-01-30","part":"xxx","proc":1,"numproc":1,"face":"1-1","serial":"00000000v7","workorder":""}],"type":"CloseOut","startofcycle":false,"endUTC":"2018-01-30T08:06:02.7158311Z","loc":"CloseOut","locnum":1,"pal":0,"program":"","result":"","elapsed":"-PT1M","active":"PT0S"},
{"counter":0,"material":[{"id":1928,"uniq":"aaa-0offline-2018-01-30","part":"aaa","proc":2,"numproc":2,"face":"2-1","serial":"00000000v6","workorder":""}],"type":"CloseOut","startofcycle":false,"endUTC":"2018-01-30T08:38:58.0981876Z","loc":"CloseOut","locnum":1,"pal":0,"program":"","result":"","elapsed":"-PT1M","active":"PT0S"},
{"counter":0,"material":[{"id":1930,"uniq":"aaa-0offline-2018-01-30","part":"aaa","proc":2,"numproc":2,"face":"2-1","serial":"00000000v8","workorder":""}],"type":"CloseOut","startofcycle":false,"endUTC":"2018-01-30T09:05:13.0092225Z","loc":"CloseOut","locnum":1,"pal":0,"program":"","result":"","elapsed":"-PT1M","active":"PT0S"},
{"counter":0,"material":[{"id":1915,"uniq":"ccc-2offline-2018-01-29","part":"ccc","proc":2,"numproc":2,"face":"2-1","serial":"00000000uT","workorder":""}],"type":"CloseOut","startofcycle":false,"endUTC":"2018-01-30T09:05:54.1885382Z","loc":"CloseOut","locnum":1,"pal":0,"program":"","result":"","elapsed":"-PT1M","active":"PT0S"},
{"counter":0,"material":[{"id":1926,"uniq":"ccc-2offline-2018-01-29","part":"ccc","proc":2,"numproc":2,"face":"2-1","serial":"00000000v4","workorder":""}],"type":"CloseOut","startofcycle":false,"endUTC":"2018-01-30T09:48:40.2122341Z","loc":"CloseOut","locnum":1,"pal":0,"program":"","result":"","elapsed":"-PT1M","active":"PT0S"},
{"counter":0,"material":[{"id":1931,"uniq":"bbb-1offline-2018-01-30","part":"bbb","proc":2,"numproc":2,"face":"2-1","serial":"00000000v9","workorder":""}],"type":"CloseOut","startofcycle":false,"endUTC":"2018-01-30T09:54:20.8109391Z","loc":"CloseOut","locnum":1,"pal":0,"program":"","result":"","elapsed":"-PT1M","active":"PT0S"},
{"counter":0,"material":[{"id":1935,"uniq":"bbb-1offline-2018-01-30","part":"bbb","proc":2,"numproc":2,"face":"2-1","serial":"00000000vd","workorder":""}],"type":"CloseOut","startofcycle":false,"endUTC":"2018-01-30T10:06:21.7851761Z","loc":"CloseOut","locnum":1,"pal":0,"program":"","result":"","elapsed":"-PT1M","active":"PT0S"},
{"counter":0,"material":[{"id":1936,"uniq":"bbb-1offline-2018-01-30","part":"bbb","proc":2,"numproc":2,"face":"2-1","serial":"00000000ve","workorder":""}],"type":"CloseOut","startofcycle":false,"endUTC":"2018-01-30T10:55:19.8646957Z","loc":"CloseOut","locnum":1,"pal":0,"program":"","result":"","elapsed":"-PT1M","active":"PT0S"},
{"counter":0,"material":[{"id":1932,"uniq":"zzz-4offline-2018-01-30","part":"zzz","proc":1,"numproc":1,"face":"1-1","serial":"00000000va","workorder":""}],"type":"CloseOut","startofcycle":false,"endUTC":"2018-01-30T11:12:24.2499806Z","loc":"CloseOut","locnum":1,"pal":0,"program":"","result":"","elapsed":"-PT1M","active":"PT0S"},
{"counter":0,"material":[{"id":1922,"uniq":"ccc-2offline-2018-01-29","part":"ccc","proc":2,"numproc":2,"face":"2-1","serial":"00000000v0","workorder":""}],"type":"CloseOut","startofcycle":false,"endUTC":"2018-01-30T11:46:17.6552837Z","loc":"CloseOut","locnum":1,"pal":0,"program":"","result":"","elapsed":"-PT1M","active":"PT0S"},
{"counter":0,"material":[{"id":1934,"uniq":"xxx-3offline-2018-01-30","part":"xxx","proc":1,"numproc":1,"face":"1-1","serial":"00000000vc","workorder":""}],"type":"CloseOut","startofcycle":false,"endUTC":"2018-01-30T12:07:12.4711081Z","loc":"CloseOut","locnum":1,"pal":0,"program":"","result":"","elapsed":"-PT1M","active":"PT0S"},
{"counter":0,"material":[{"id":1933,"uniq":"ccc-2offline-2018-01-29","part":"ccc","proc":2,"numproc":2,"face":"2-1","serial":"00000000vb","workorder":""}],"type":"CloseOut","startofcycle":false,"endUTC":"2018-01-30T12:15:54.3883789Z","loc":"CloseOut","locnum":1,"pal":0,"program":"","result":"","elapsed":"-PT1M","active":"PT0S"},
{"counter":0,"material":[{"id":1940,"uniq":"bbb-1offline-2018-01-30","part":"bbb","proc":2,"numproc":2,"face":"2-1","serial":"00000000vi","workorder":""}],"type":"CloseOut","startofcycle":false,"endUTC":"2018-01-30T12:18:31.6916393Z","loc":"CloseOut","locnum":1,"pal":0,"program":"","result":"","elapsed":"-PT1M","active":"PT0S"},
{"counter":0,"material":[{"id":1937,"uniq":"bbb-1offline-2018-01-30","part":"bbb","proc":2,"numproc":2,"face":"2-1","serial":"00000000vf","workorder":""}],"type":"CloseOut","startofcycle":false,"endUTC":"2018-01-30T12:32:42.8621806Z","loc":"CloseOut","locnum":1,"pal":0,"program":"","result":"","elapsed":"-PT1M","active":"PT0S"},
{"counter":0,"material":[{"id":1938,"uniq":"ccc-2offline-2018-01-30","part":"ccc","proc":2,"numproc":2,"face":"2-1","serial":"00000000vg","workorder":""}],"type":"CloseOut","startofcycle":false,"endUTC":"2018-01-30T14:05:13.0478882Z","loc":"CloseOut","locnum":1,"pal":0,"program":"","result":"","elapsed":"-PT1M","active":"PT0S"},
{"counter":0,"material":[{"id":1939,"uniq":"ccc-2offline-2018-01-30","part":"ccc","proc":2,"numproc":2,"face":"2-1","serial":"00000000vh","workorder":""}],"type":"CloseOut","startofcycle":false,"endUTC":"2018-01-30T14:23:09.5048523Z","loc":"CloseOut","locnum":1,"pal":0,"program":"","result":"","elapsed":"-PT1M","active":"PT0S"},
{"counter":0,"material":[{"id":1941,"uniq":"bbb-1offline-2018-01-30","part":"bbb","proc":2,"numproc":2,"face":"2-1","serial":"00000000vj","workorder":""}],"type":"CloseOut","startofcycle":false,"endUTC":"2018-01-30T15:10:54.8968947Z","loc":"CloseOut","locnum":1,"pal":0,"program":"","result":"","elapsed":"-PT1M","active":"PT0S"},
{"counter":0,"material":[{"id":1943,"uniq":"zzz-4offline-2018-01-30","part":"zzz","proc":1,"numproc":1,"face":"1-1","serial":"00000000vl","workorder":""}],"type":"CloseOut","startofcycle":false,"endUTC":"2018-01-30T15:25:36.6898707Z","loc":"CloseOut","locnum":1,"pal":0,"program":"","result":"","elapsed":"-PT1M","active":"PT0S"},
{"counter":0,"material":[{"id":1945,"uniq":"zzz-4offline-2018-01-30","part":"zzz","proc":1,"numproc":1,"face":"1-1","serial":"00000000vn","workorder":""}],"type":"CloseOut","startofcycle":false,"endUTC":"2018-01-30T15:29:30.0157059Z","loc":"CloseOut","locnum":1,"pal":0,"program":"","result":"","elapsed":"-PT1M","active":"PT0S"},
{"counter":0,"material":[{"id":1944,"uniq":"ccc-2offline-2018-01-30","part":"ccc","proc":2,"numproc":2,"face":"2-1","serial":"00000000vm","workorder":""}],"type":"CloseOut","startofcycle":false,"endUTC":"2018-01-30T16:06:46.3030368Z","loc":"CloseOut","locnum":1,"pal":0,"program":"","result":"","elapsed":"-PT1M","active":"PT0S"},
{"counter":0,"material":[{"id":1942,"uniq":"bbb-1offline-2018-01-30","part":"bbb","proc":2,"numproc":2,"face":"2-1","serial":"00000000vk","workorder":""}],"type":"CloseOut","startofcycle":false,"endUTC":"2018-01-30T16:23:26.9576174Z","loc":"CloseOut","locnum":1,"pal":0,"program":"","result":"","elapsed":"-PT1M","active":"PT0S"},
{"counter":0,"material":[{"id":1946,"uniq":"ccc-2offline-2018-01-30","part":"ccc","proc":2,"numproc":2,"face":"2-1","serial":"00000000vo","workorder":""}],"type":"CloseOut","startofcycle":false,"endUTC":"2018-01-30T17:00:52.8469048Z","loc":"CloseOut","locnum":1,"pal":0,"program":"","result":"","elapsed":"-PT1M","active":"PT0S"},
{"counter":0,"material":[{"id":1947,"uniq":"bbb-1offline-2018-01-30","part":"bbb","proc":2,"numproc":2,"face":"2-1","serial":"00000000vp","workorder":""}],"type":"CloseOut","startofcycle":false,"endUTC":"2018-01-30T17:24:03.4942442Z","loc":"CloseOut","locnum":1,"pal":0,"program":"","result":"","elapsed":"-PT1M","active":"PT0S"},
{"counter":0,"material":[{"id":1948,"uniq":"bbb-1offline-2018-01-30","part":"bbb","proc":2,"numproc":2,"face":"2-1","serial":"00000000vq","workorder":""}],"type":"CloseOut","startofcycle":false,"endUTC":"2018-01-30T17:48:42.9397826Z","loc":"CloseOut","locnum":1,"pal":0,"program":"","result":"","elapsed":"-PT1M","active":"PT0S"},
{"counter":0,"material":[{"id":1955,"uniq":"bbb-1offline-2018-01-30","part":"bbb","proc":2,"numproc":2,"face":"2-1","serial":"00000000vx","workorder":""}],"type":"CloseOut","startofcycle":false,"endUTC":"2018-01-30T18:21:55.445309Z","loc":"CloseOut","locnum":1,"pal":0,"program":"","result":"","elapsed":"-PT1M","active":"PT0S"},
{"counter":0,"material":[{"id":1952,"uniq":"zzz-4offline-2018-01-30","part":"zzz","proc":1,"numproc":1,"face":"1-1","serial":"00000000vu","workorder":""}],"type":"CloseOut","startofcycle":false,"endUTC":"2018-01-30T18:50:26.083763Z","loc":"CloseOut","locnum":1,"pal":0,"program":"","result":"","elapsed":"-PT1M","active":"PT0S"},
{"counter":0,"material":[{"id":1951,"uniq":"bbb-1offline-2018-01-30","part":"bbb","proc":2,"numproc":2,"face":"2-1","serial":"00000000vt","workorder":""}],"type":"CloseOut","startofcycle":false,"endUTC":"2018-01-30T18:56:00.6811362Z","loc":"CloseOut","locnum":1,"pal":0,"program":"","result":"","elapsed":"-PT1M","active":"PT0S"},
{"counter":0,"material":[{"id":1950,"uniq":"ccc-2offline-2018-01-30","part":"ccc","proc":2,"numproc":2,"face":"2-1","serial":"00000000vs","workorder":""}],"type":"CloseOut","startofcycle":false,"endUTC":"2018-01-30T19:38:40.6886288Z","loc":"CloseOut","locnum":1,"pal":0,"program":"","result":"","elapsed":"-PT1M","active":"PT0S"},
{"counter":0,"material":[{"id":1957,"uniq":"bbb-1offline-2018-01-30","part":"bbb","proc":2,"numproc":2,"face":"2-1","serial":"00000000vz","workorder":""}],"type":"CloseOut","startofcycle":false,"endUTC":"2018-01-30T19:45:04.605268Z","loc":"CloseOut","locnum":1,"pal":0,"program":"","result":"","elapsed":"-PT1M","active":"PT0S"},
{"counter":0,"material":[{"id":1954,"uniq":"ccc-2offline-2018-01-30","part":"ccc","proc":2,"numproc":2,"face":"2-1","serial":"00000000vw","workorder":""}],"type":"CloseOut","startofcycle":false,"endUTC":"2018-01-30T20:12:34.7668071Z","loc":"CloseOut","locnum":1,"pal":0,"program":"","result":"","elapsed":"-PT1M","active":"PT0S"},
{"counter":0,"material":[{"id":1956,"uniq":"ccc-2offline-2018-01-30","part":"ccc","proc":2,"numproc":2,"face":"2-1","serial":"00000000vy","workorder":""}],"type":"CloseOut","startofcycle":false,"endUTC":"2018-01-30T22:00:43.7337727Z","loc":"CloseOut","locnum":1,"pal":0,"program":"","result":"","elapsed":"-PT1M","active":"PT0S"},
{"counter":0,"material":[{"id":1959,"uniq":"zzz-4offline-2018-01-30","part":"zzz","proc":1,"numproc":1,"face":"1-1","serial":"00000000vB","workorder":""}],"type":"CloseOut","startofcycle":false,"endUTC":"2018-01-30T22:51:27.3299523Z","loc":"CloseOut","locnum":1,"pal":0,"program":"","result":"","elapsed":"-PT1M","active":"PT0S"},
{"counter":0,"material":[{"id":1958,"uniq":"ccc-2offline-2018-01-30","part":"ccc","proc":2,"numproc":2,"face":"2-1","serial":"00000000vA","workorder":""}],"type":"CloseOut","startofcycle":false,"endUTC":"2018-01-30T23:51:49.3784021Z","loc":"CloseOut","locnum":1,"pal":0,"program":"","result":"","elapsed":"-PT1M","active":"PT0S"},
{"counter":0,"material":[{"id":1960,"uniq":"ccc-2offline-2018-01-30","part":"ccc","proc":2,"numproc":2,"face":"2-1","serial":"00000000vC","workorder":""}],"type":"CloseOut","startofcycle":false,"endUTC":"2018-01-31T01:42:45.3744502Z","loc":"CloseOut","locnum":1,"pal":0,"program":"","result":"","elapsed":"-PT1M","active":"PT0S"},
{"counter":0,"material":[{"id":1964,"uniq":"zzz-4offline-2018-01-30","part":"zzz","proc":1,"numproc":1,"face":"1-1","serial":"00000000vG","workorder":""}],"type":"CloseOut","startofcycle":false,"endUTC":"2018-01-31T02:16:39.4237194Z","loc":"CloseOut","locnum":1,"pal":0,"program":"","result":"","elapsed":"-PT1M","active":"PT0S"},
{"counter":0,"material":[{"id":1962,"uniq":"ccc-2offline-2018-01-30","part":"ccc","proc":2,"numproc":2,"face":"2-1","serial":"00000000vE","workorder":""}],"type":"CloseOut","startofcycle":false,"endUTC":"2018-01-31T03:44:57.3362555Z","loc":"CloseOut","locnum":1,"pal":0,"program":"","result":"","elapsed":"-PT1M","active":"PT0S"},
{"counter":0,"material":[{"id":1961,"uniq":"ccc-2offline-2018-01-30","part":"ccc","proc":2,"numproc":2,"face":"2-1","serial":"00000000vD","workorder":""}],"type":"CloseOut","startofcycle":false,"endUTC":"2018-01-31T04:26:33.1827587Z","loc":"CloseOut","locnum":1,"pal":0,"program":"","result":"","elapsed":"-PT1M","active":"PT0S"},
{"counter":0,"material":[{"id":1967,"uniq":"zzz-4offline-2018-01-30","part":"zzz","proc":1,"numproc":1,"face":"1-1","serial":"00000000vJ","workorder":""}],"type":"CloseOut","startofcycle":false,"endUTC":"2018-01-31T04:59:50.601603Z","loc":"CloseOut","locnum":1,"pal":0,"program":"","result":"","elapsed":"-PT1M","active":"PT0S"},
{"counter":0,"material":[{"id":1968,"uniq":"zzz-4offline-2018-01-30","part":"zzz","proc":1,"numproc":1,"face":"1-1","serial":"00000000vK","workorder":""}],"type":"CloseOut","startofcycle":false,"endUTC":"2018-01-31T05:34:11.7473286Z","loc":"CloseOut","locnum":1,"pal":0,"program":"","result":"","elapsed":"-PT1M","active":"PT0S"},
{"counter":0,"material":[{"id":1966,"uniq":"ccc-2offline-2018-01-30","part":"ccc","proc":2,"numproc":2,"face":"2-1","serial":"00000000vI","workorder":""}],"type":"CloseOut","startofcycle":false,"endUTC":"2018-01-31T05:45:33.0742933Z","loc":"CloseOut","locnum":1,"pal":0,"program":"","result":"","elapsed":"-PT1M","active":"PT0S"},
{"counter":0,"material":[{"id":1969,"uniq":"ccc-2offline-2018-01-30","part":"ccc","proc":2,"numproc":2,"face":"2-1","serial":"00000000vL","workorder":""}],"type":"CloseOut","startofcycle":false,"endUTC":"2018-01-31T06:20:18.6221756Z","loc":"CloseOut","locnum":1,"pal":0,"program":"","result":"","elapsed":"-PT1M","active":"PT0S"},
{"counter":0,"material":[{"id":1965,"uniq":"ccc-2offline-2018-01-30","part":"ccc","proc":2,"numproc":2,"face":"2-1","serial":"00000000vH","workorder":""}],"type":"CloseOut","startofcycle":false,"endUTC":"2018-01-31T06:26:43.6421679Z","loc":"CloseOut","locnum":1,"pal":0,"program":"","result":"","elapsed":"-PT1M","active":"PT0S"},
{"counter":0,"material":[{"id":1970,"uniq":"ccc-2offline-2018-01-30","part":"ccc","proc":2,"numproc":2,"face":"2-1","serial":"00000000vM","workorder":""}],"type":"CloseOut","startofcycle":false,"endUTC":"2018-01-31T07:02:17.268407Z","loc":"CloseOut","locnum":1,"pal":0,"program":"","result":"","elapsed":"-PT1M","active":"PT0S"}
]