{"Alarms":[],"Jobs":{"aaa-offline-2018-01-10":{"Archived":false,"Bookings":["aaa-18","bbb-12","ccc-12","yyy-8","zzz-4"],"Comment":"","CopiedToSystem":false,"CreateMarkingData":false,"CyclesOnFirstProcess":[11],"HoldEntireJob":{"HoldUnholdPattern":[],"HoldUnholdPatternRepeats":false,"HoldUnholdPatternStartUTC":"2000-01-01T00:00:00Z","ReasonForUserHold":"","UserHold":false},"Inspections":[{"Counter":"aaa,3DScan,P%pal1%,S%stat1,1%,P%pal2%,S%stat2,1%","InspectSingleProcess":-1,"InspectionType":"3DScan","MaxVal":-1,"RandomFreq":0,"TimeInterval":"P1DT12H"},{"Counter":"aaa,CMM,P%pal1%,S%stat1,1%,P%pal2%,S%stat2,1%","InspectSingleProcess":-1,"InspectionType":"CMM","MaxVal":10,"RandomFreq":-1,"TimeInterval":"PT0S"}],"ManuallyCreated":false,"PartName":"aaa","Priority":100,"ProcsAndPaths":[{"paths":[{"Fixtures":[{"Face":"1","Fixture":"7f54f3ce-bfb5-50d0-8986-83f2b197c62e"}],"HoldLoadUnload":{"HoldUnholdPattern":[],"HoldUnholdPatternRepeats":false,"HoldUnholdPatternStartUTC":"2000-01-01T00:00:00Z","ReasonForUserHold":"","UserHold":false},"HoldMachining":{"HoldUnholdPattern":[],"HoldUnholdPatternRepeats":false,"HoldUnholdPatternStartUTC":"2000-01-01T00:00:00Z","ReasonForUserHold":"","UserHold":false},"Load":[1,2],"Pallets":["1","2","3","4"],"PartsPerPallet":1,"PathGroup":0,"SimulatedAverageFlowTime":"PT1H36M44.7272727S","SimulatedProduction":[{"Quantity":1,"TimeUTC":"2018-01-10T11:27:40Z"},{"Quantity":2,"TimeUTC":"2018-01-10T12:44:50Z"},{"Quantity":3,"TimeUTC":"2018-01-10T13:08:38Z"},{"Quantity":4,"TimeUTC":"2018-01-10T13:59:58Z"},{"Quantity":5,"TimeUTC":"2018-01-10T14:17:32Z"},{"Quantity":6,"TimeUTC":"2018-01-10T14:22:30Z"},{"Quantity":7,"TimeUTC":"2018-01-10T14:40:04Z"},{"Quantity":8,"TimeUTC":"2018-01-10T14:57:36Z"},{"Quantity":9,"TimeUTC":"2018-01-10T15:15:08Z"},{"Quantity":10,"TimeUTC":"2018-01-10T15:22:34Z"},{"Quantity":11,"TimeUTC":"2018-01-10T15:41:22Z"}],"SimulatedStartingUTC":"2018-01-10T11:27:40Z","Stops":[{"ExpectedCycleTime":"PT12M12S","StationGroup":"Machine","Stations":{"1":"100","2":"100","3":"100","4":"100"},"Tools":{}}],"Unload":[1,2]}]},{"paths":[{"Fixtures":[{"Face":"2","Fixture":"7f54f3ce-bfb5-50d0-8986-83f2b197c62e"}],"HoldLoadUnload":{"HoldUnholdPattern":[],"HoldUnholdPatternRepeats":false,"HoldUnholdPatternStartUTC":"2000-01-01T00:00:00Z","ReasonForUserHold":"","UserHold":false},"HoldMachining":{"HoldUnholdPattern":[],"HoldUnholdPatternRepeats":false,"HoldUnholdPatternStartUTC":"2000-01-01T00:00:00Z","ReasonForUserHold":"","UserHold":false},"Load":[1,2],"Pallets":["1","2","3","4"],"PartsPerPallet":1,"PathGroup":0,"SimulatedAverageFlowTime":"PT1H10M17.2727272S","SimulatedProduction":[{"Quantity":1,"TimeUTC":"2018-01-10T13:08:38Z"},{"Quantity":2,"TimeUTC":"2018-01-10T13:59:58Z"},{"Quantity":3,"TimeUTC":"2018-01-10T14:17:32Z"},{"Quantity":4,"TimeUTC":"2018-01-10T14:57:36Z"},{"Quantity":5,"TimeUTC":"2018-01-10T15:15:08Z"},{"Quantity":6,"TimeUTC":"2018-01-10T15:22:34Z"},{"Quantity":7,"TimeUTC":"2018-01-10T15:22:40Z"},{"Quantity":8,"TimeUTC":"2018-01-10T15:32:38Z"},{"Quantity":9,"TimeUTC":"2018-01-10T15:40:10Z"},{"Quantity":10,"TimeUTC":"2018-01-10T15:41:22Z"},{"Quantity":11,"TimeUTC":"2018-01-10T16:12:46Z"}],"SimulatedStartingUTC":"2018-01-10T13:08:38Z","Stops":[{"ExpectedCycleTime":"PT9M18S","StationGroup":"Machine","Stations":{"1":"200","2":"200","3":"200","4":"200"},"Tools":{}}],"Unload":[1,2]}]}],"RouteEndUTC":"2018-01-10T18:00:00Z","RouteStartUTC":"2018-01-09T18:00:00Z","ScheduleId":"offline-2018-01-10","Unique":"aaa-offline-2018-01-10","Completed":[[0],[0]]},"bbb-offline-2018-01-10":{"Archived":false,"Bookings":["aaa-18","bbb-12","ccc-12","yyy-8","zzz-4"],"Comment":"","CopiedToSystem":false,"CreateMarkingData":false,"CyclesOnFirstProcess":[18],"HoldEntireJob":{"HoldUnholdPattern":[],"HoldUnholdPatternRepeats":false,"HoldUnholdPatternStartUTC":"2000-01-01T00:00:00Z","ReasonForUserHold":"","UserHold":false},"Inspections":[{"Counter":"bbb,3DScan,P%pal1%,S%stat1,1%,P%pal2%,S%stat2,1%","InspectSingleProcess":-1,"InspectionType":"3DScan","MaxVal":-1,"RandomFreq":0,"TimeInterval":"P3D"},{"Counter":"bbb,CMM,P%pal1%,S%stat1,1%,P%pal2%,S%stat2,1%","InspectSingleProcess":-1,"InspectionType":"CMM","MaxVal":15,"RandomFreq":-1,"TimeInterval":"PT0S"}],"ManuallyCreated":false,"PartName":"bbb","Priority":100,"ProcsAndPaths":[{"paths":[{"Fixtures":[{"Face":"1","Fixture":"7f54f3ce-bfb5-50d0-8986-83f2b197c62e"}],"HoldLoadUnload":{"HoldUnholdPattern":[],"HoldUnholdPatternRepeats":false,"HoldUnholdPatternStartUTC":"2000-01-01T00:00:00Z","ReasonForUserHold":"","UserHold":false},"HoldMachining":{"HoldUnholdPattern":[],"HoldUnholdPatternRepeats":false,"HoldUnholdPatternStartUTC":"2000-01-01T00:00:00Z","ReasonForUserHold":"","UserHold":false},"Load":[1,2],"Pallets":["1","2","3","4"],"PartsPerPallet":1,"PathGroup":0,"SimulatedAverageFlowTime":"PT1H56M30.6666666S","SimulatedProduction":[{"Quantity":1,"TimeUTC":"2018-01-10T04:59:38Z"},{"Quantity":2,"TimeUTC":"2018-01-10T05:00:54Z"},{"Quantity":3,"TimeUTC":"2018-01-10T05:51:52Z"},{"Quantity":4,"TimeUTC":"2018-01-10T06:11:32Z"},{"Quantity":5,"TimeUTC":"2018-01-10T07:09:02Z"},{"Quantity":6,"TimeUTC":"2018-01-10T07:12:50Z"},{"Quantity":7,"TimeUTC":"2018-01-10T07:31:34Z"},{"Quantity":8,"TimeUTC":"2018-01-10T07:35:44Z"},{"Quantity":9,"TimeUTC":"2018-01-10T07:55:54Z"},{"Quantity":10,"TimeUTC":"2018-01-10T08:26:12Z"},{"Quantity":11,"TimeUTC":"2018-01-10T08:50:22Z"},{"Quantity":12,"TimeUTC":"2018-01-10T08:51:38Z"},{"Quantity":13,"TimeUTC":"2018-01-10T10:07:32Z"},{"Quantity":14,"TimeUTC":"2018-01-10T10:08:48Z"},{"Quantity":15,"TimeUTC":"2018-01-10T10:32:36Z"},{"Quantity":16,"TimeUTC":"2018-01-10T10:43:52Z"},{"Quantity":17,"TimeUTC":"2018-01-10T12:46:06Z"},{"Quantity":18,"TimeUTC":"2018-01-10T13:09:54Z"}],"SimulatedStartingUTC":"2018-01-10T04:59:38Z","Stops":[{"ExpectedCycleTime":"PT4M","StationGroup":"Machine","Stations":{"1":"300","2":"300","3":"300","4":"300"},"Tools":{}}],"Unload":[1,2]}]},{"paths":[{"Fixtures":[{"Face":"2","Fixture":"7f54f3ce-bfb5-50d0-8986-83f2b197c62e"}],"HoldLoadUnload":{"HoldUnholdPattern":[],"HoldUnholdPatternRepeats":false,"HoldUnholdPatternStartUTC":"2000-01-01T00:00:00Z","ReasonForUserHold":"","UserHold":false},"HoldMachining":{"HoldUnholdPattern":[],"HoldUnholdPatternRepeats":false,"HoldUnholdPatternStartUTC":"2000-01-01T00:00:00Z","ReasonForUserHold":"","UserHold":false},"Load":[1,2],"Pallets":["1","2","3","4"],"PartsPerPallet":1,"PathGroup":0,"SimulatedAverageFlowTime":"PT1H59M39.8888888S","SimulatedProduction":[{"Quantity":1,"TimeUTC":"2018-01-10T05:51:52Z"},{"Quantity":2,"TimeUTC":"2018-01-10T07:12:50Z"},{"Quantity":3,"TimeUTC":"2018-01-10T07:31:34Z"},{"Quantity":4,"TimeUTC":"2018-01-10T07:35:44Z"},{"Quantity":5,"TimeUTC":"2018-01-10T07:55:54Z"},{"Quantity":6,"TimeUTC":"2018-01-10T08:26:12Z"},{"Quantity":7,"TimeUTC":"2018-01-10T08:50:22Z"},{"Quantity":8,"TimeUTC":"2018-01-10T08:51:38Z"},{"Quantity":9,"TimeUTC":"2018-01-10T10:07:32Z"},{"Quantity":10,"TimeUTC":"2018-01-10T10:08:48Z"},{"Quantity":11,"TimeUTC":"2018-01-10T10:32:36Z"},{"Quantity":12,"TimeUTC":"2018-01-10T10:43:52Z"},{"Quantity":13,"TimeUTC":"2018-01-10T11:27:40Z"},{"Quantity":14,"TimeUTC":"2018-01-10T12:44:50Z"},{"Quantity":15,"TimeUTC":"2018-01-10T12:46:06Z"},{"Quantity":16,"TimeUTC":"2018-01-10T13:09:54Z"},{"Quantity":17,"TimeUTC":"2018-01-10T14:22:30Z"},{"Quantity":18,"TimeUTC":"2018-01-10T14:40:04Z"}],"SimulatedStartingUTC":"2018-01-10T05:51:52Z","Stops":[{"ExpectedCycleTime":"PT20M","StationGroup":"Machine","Stations":{"1":"400","2":"400","3":"400","4":"400"},"Tools":{}}],"Unload":[1,2]}]}],"RouteEndUTC":"2018-01-10T18:00:00Z","RouteStartUTC":"2018-01-09T18:00:00Z","ScheduleId":"offline-2018-01-10","Unique":"bbb-offline-2018-01-10","Completed":[[3],[1]]},"ccc-offline-2018-01-10":{"Archived":false,"Bookings":["aaa-18","bbb-12","ccc-12","yyy-8","zzz-4"],"Comment":"","CopiedToSystem":false,"CreateMarkingData":false,"CyclesOnFirstProcess":[18],"HoldEntireJob":{"HoldUnholdPattern":[],"HoldUnholdPatternRepeats":false,"HoldUnholdPatternStartUTC":"2000-01-01T00:00:00Z","ReasonForUserHold":"","UserHold":false},"Inspections":[{"Counter":"ccc,3DScan,P%pal1%,S%stat1,1%,P%pal2%,S%stat2,1%","InspectSingleProcess":-1,"InspectionType":"3DScan","MaxVal":-1,"RandomFreq":0.05,"TimeInterval":"PT0S"},{"Counter":"ccc,CMM,P%pal1%,S%stat1,1%,P%pal2%,S%stat2,1%","InspectSingleProcess":-1,"InspectionType":"CMM","MaxVal":5,"RandomFreq":-1,"TimeInterval":"PT0S"}],"ManuallyCreated":false,"PartName":"ccc","Priority":100,"ProcsAndPaths":[{"paths":[{"Fixtures":[{"Face":"1","Fixture":"7f54f3ce-bfb5-50d0-8986-83f2b197c62e"}],"HoldLoadUnload":{"HoldUnholdPattern":[],"HoldUnholdPatternRepeats":false,"HoldUnholdPatternStartUTC":"2000-01-01T00:00:00Z","ReasonForUserHold":"","UserHold":false},"HoldMachining":{"HoldUnholdPattern":[],"HoldUnholdPatternRepeats":false,"HoldUnholdPatternStartUTC":"2000-01-01T00:00:00Z","ReasonForUserHold":"","UserHold":false},"Load":[1,2],"Pallets":["1","2","3","4"],"PartsPerPallet":1,"PathGroup":0,"SimulatedAverageFlowTime":"PT2H29M58.8888888S","SimulatedProduction":[{"Quantity":1,"TimeUTC":"2018-01-09T20:30:06Z"},{"Quantity":2,"TimeUTC":"2018-01-09T20:31:22Z"},{"Quantity":3,"TimeUTC":"2018-01-09T20:48:54Z"},{"Quantity":4,"TimeUTC":"2018-01-09T20:50:10Z"},{"Quantity":5,"TimeUTC":"2018-01-09T22:49:12Z"},{"Quantity":6,"TimeUTC":"2018-01-09T22:50:28Z"},{"Quantity":7,"TimeUTC":"2018-01-09T23:13:00Z"},{"Quantity":8,"TimeUTC":"2018-01-09T23:14:16Z"},{"Quantity":9,"TimeUTC":"2018-01-10T01:02:02Z"},{"Quantity":10,"TimeUTC":"2018-01-10T01:03:18Z"},{"Quantity":11,"TimeUTC":"2018-01-10T01:25:50Z"},{"Quantity":12,"TimeUTC":"2018-01-10T01:27:06Z"},{"Quantity":13,"TimeUTC":"2018-01-10T03:14:52Z"},{"Quantity":14,"TimeUTC":"2018-01-10T03:16:08Z"},{"Quantity":15,"TimeUTC":"2018-01-10T03:38:40Z"},{"Quantity":16,"TimeUTC":"2018-01-10T03:39:56Z"},{"Quantity":17,"TimeUTC":"2018-01-10T05:27:42Z"},{"Quantity":18,"TimeUTC":"2018-01-10T05:28:58Z"}],"SimulatedStartingUTC":"2018-01-09T20:30:06Z","Stops":[{"ExpectedCycleTime":"PT40M","StationGroup":"Machine","Stations":{"1":"300","2":"300","3":"300","4":"300"},"Tools":{}}],"Unload":[1,2]}]},{"paths":[{"Fixtures":[{"Face":"2","Fixture":"7f54f3ce-bfb5-50d0-8986-83f2b197c62e"}],"HoldLoadUnload":{"HoldUnholdPattern":[],"HoldUnholdPatternRepeats":false,"HoldUnholdPatternStartUTC":"2000-01-01T00:00:00Z","ReasonForUserHold":"","UserHold":false},"HoldMachining":{"HoldUnholdPattern":[],"HoldUnholdPatternRepeats":false,"HoldUnholdPatternStartUTC":"2000-01-01T00:00:00Z","ReasonForUserHold":"","UserHold":false},"Load":[1,2],"Pallets":["1","2","3","4"],"PartsPerPallet":1,"PathGroup":0,"SimulatedAverageFlowTime":"PT2H21M8.5555555S","SimulatedProduction":[{"Quantity":1,"TimeUTC":"2018-01-09T22:49:12Z"},{"Quantity":2,"TimeUTC":"2018-01-09T22:50:28Z"},{"Quantity":3,"TimeUTC":"2018-01-09T23:13:00Z"},{"Quantity":4,"TimeUTC":"2018-01-09T23:14:16Z"},{"Quantity":5,"TimeUTC":"2018-01-10T01:02:02Z"},{"Quantity":6,"TimeUTC":"2018-01-10T01:03:18Z"},{"Quantity":7,"TimeUTC":"2018-01-10T01:25:50Z"},{"Quantity":8,"TimeUTC":"2018-01-10T01:27:06Z"},{"Quantity":9,"TimeUTC":"2018-01-10T03:14:52Z"},{"Quantity":10,"TimeUTC":"2018-01-10T03:16:08Z"},{"Quantity":11,"TimeUTC":"2018-01-10T03:38:40Z"},{"Quantity":12,"TimeUTC":"2018-01-10T03:39:56Z"},{"Quantity":13,"TimeUTC":"2018-01-10T04:59:38Z"},{"Quantity":14,"TimeUTC":"2018-01-10T05:00:54Z"},{"Quantity":15,"TimeUTC":"2018-01-10T05:27:42Z"},{"Quantity":16,"TimeUTC":"2018-01-10T05:28:58Z"},{"Quantity":17,"TimeUTC":"2018-01-10T06:11:32Z"},{"Quantity":18,"TimeUTC":"2018-01-10T07:09:02Z"}],"SimulatedStartingUTC":"2018-01-09T22:49:12Z","Stops":[{"ExpectedCycleTime":"PT15M30S","StationGroup":"Machine","Stations":{"1":"400","2":"400","3":"400","4":"400"},"Tools":{}}],"Unload":[1,2]}]}],"RouteEndUTC":"2018-01-10T18:00:00Z","RouteStartUTC":"2018-01-09T18:00:00Z","ScheduleId":"offline-2018-01-10","Unique":"ccc-offline-2018-01-10","Completed":[[18],[16]]},"yyy-offline-2018-01-10":{"Archived":false,"Bookings":["aaa-18","bbb-12","ccc-12","yyy-8","zzz-4"],"Comment":"","CopiedToSystem":false,"CreateMarkingData":false,"CyclesOnFirstProcess":[12],"HoldEntireJob":{"HoldUnholdPattern":[],"HoldUnholdPatternRepeats":false,"HoldUnholdPatternStartUTC":"2000-01-01T00:00:00Z","ReasonForUserHold":"","UserHold":false},"Inspections":[],"ManuallyCreated":false,"PartName":"yyy","Priority":100,"ProcsAndPaths":[{"paths":[{"Fixtures":[{"Face":"1","Fixture":"7f54f3ce-bfb5-50d0-8986-83f2b197c62e"}],"HoldLoadUnload":{"HoldUnholdPattern":[],"HoldUnholdPatternRepeats":false,"HoldUnholdPatternStartUTC":"2000-01-01T00:00:00Z","ReasonForUserHold":"","UserHold":false},"HoldMachining":{"HoldUnholdPattern":[],"HoldUnholdPatternRepeats":false,"HoldUnholdPatternStartUTC":"2000-01-01T00:00:00Z","ReasonForUserHold":"","UserHold":false},"Load":[1,2],"Pallets":["5","6","7","8"],"PartsPerPallet":2,"PathGroup":0,"SimulatedAverageFlowTime":"PT1H40M34.1666666S","SimulatedProduction":[{"Quantity":2,"TimeUTC":"2018-01-10T13:55:00Z"},{"Quantity":4,"TimeUTC":"2018-01-10T15:05:02Z"},{"Quantity":6,"TimeUTC":"2018-01-10T16:03:58Z"},{"Quantity":8,"TimeUTC":"2018-01-10T16:05:14Z"},{"Quantity":10,"TimeUTC":"2018-01-10T16:29:02Z"},{"Quantity":12,"TimeUTC":"2018-01-10T16:35:18Z"}],"SimulatedStartingUTC":"2018-01-10T13:55:00Z","Stops":[{"ExpectedCycleTime":"PT50M","StationGroup":"Machine","Stations":{"1":"500","2":"500","3":"500","4":"500"},"Tools":{}}],"Unload":[1,2]}]}],"RouteEndUTC":"2018-01-10T18:00:00Z","RouteStartUTC":"2018-01-09T18:00:00Z","ScheduleId":"offline-2018-01-10","Unique":"yyy-offline-2018-01-10","Completed":[[0]]},"zzz-offline-2018-01-10":{"Archived":false,"Bookings":["aaa-18","bbb-12","ccc-12","yyy-8","zzz-4"],"Comment":"","CopiedToSystem":false,"CreateMarkingData":false,"CyclesOnFirstProcess":[31],"HoldEntireJob":{"HoldUnholdPattern":[],"HoldUnholdPatternRepeats":false,"HoldUnholdPatternStartUTC":"2000-01-01T00:00:00Z","ReasonForUserHold":"","UserHold":false},"Inspections":[],"ManuallyCreated":false,"PartName":"zzz","Priority":100,"ProcsAndPaths":[{"paths":[{"Fixtures":[{"Face":"1","Fixture":"7f54f3ce-bfb5-50d0-8986-83f2b197c62e"}],"HoldLoadUnload":{"HoldUnholdPattern":[],"HoldUnholdPatternRepeats":false,"HoldUnholdPatternStartUTC":"2000-01-01T00:00:00Z","ReasonForUserHold":"","UserHold":false},"HoldMachining":{"HoldUnholdPattern":[],"HoldUnholdPatternRepeats":false,"HoldUnholdPatternStartUTC":"2000-01-01T00:00:00Z","ReasonForUserHold":"","UserHold":false},"Load":[1,2],"Pallets":["5","6","7","8"],"PartsPerPallet":1,"PathGroup":0,"SimulatedAverageFlowTime":"PT2H27M28.0645161S","SimulatedProduction":[{"Quantity":1,"TimeUTC":"2018-01-09T19:44:56Z"},{"Quantity":2,"TimeUTC":"2018-01-09T19:46:12Z"},{"Quantity":3,"TimeUTC":"2018-01-09T19:58:44Z"},{"Quantity":4,"TimeUTC":"2018-01-09T20:00:00Z"},{"Quantity":5,"TimeUTC":"2018-01-09T21:43:32Z"},{"Quantity":6,"TimeUTC":"2018-01-09T21:44:48Z"},{"Quantity":7,"TimeUTC":"2018-01-09T21:57:20Z"},{"Quantity":8,"TimeUTC":"2018-01-09T21:58:36Z"},{"Quantity":9,"TimeUTC":"2018-01-09T23:56:22Z"},{"Quantity":10,"TimeUTC":"2018-01-09T23:57:38Z"},{"Quantity":11,"TimeUTC":"2018-01-10T00:10:10Z"},{"Quantity":12,"TimeUTC":"2018-01-10T00:11:26Z"},{"Quantity":13,"TimeUTC":"2018-01-10T02:09:12Z"},{"Quantity":14,"TimeUTC":"2018-01-10T02:10:28Z"},{"Quantity":15,"TimeUTC":"2018-01-10T02:23:00Z"},{"Quantity":16,"TimeUTC":"2018-01-10T02:24:16Z"},{"Quantity":17,"TimeUTC":"2018-01-10T04:22:02Z"},{"Quantity":18,"TimeUTC":"2018-01-10T04:23:18Z"},{"Quantity":19,"TimeUTC":"2018-01-10T04:35:50Z"},{"Quantity":20,"TimeUTC":"2018-01-10T04:37:06Z"},{"Quantity":21,"TimeUTC":"2018-01-10T06:36:08Z"},{"Quantity":22,"TimeUTC":"2018-01-10T06:37:24Z"},{"Quantity":23,"TimeUTC":"2018-01-10T06:49:56Z"},{"Quantity":24,"TimeUTC":"2018-01-10T08:17:28Z"},{"Quantity":25,"TimeUTC":"2018-01-10T09:04:10Z"},{"Quantity":26,"TimeUTC":"2018-01-10T09:05:26Z"},{"Quantity":27,"TimeUTC":"2018-01-10T10:21:20Z"},{"Quantity":28,"TimeUTC":"2018-01-10T11:00:08Z"},{"Quantity":29,"TimeUTC":"2018-01-10T11:33:56Z"},{"Quantity":30,"TimeUTC":"2018-01-10T11:55:12Z"},{"Quantity":31,"TimeUTC":"2018-01-10T13:37:26Z"}],"SimulatedStartingUTC":"2018-01-09T19:44:56Z","Stops":[{"ExpectedCycleTime":"PT1H17M","StationGroup":"Machine","Stations":{"1":"500","2":"500","3":"500","4":"500"},"Tools":{}}],"Unload":[1,2]}]}],"RouteEndUTC":"2018-01-10T18:00:00Z","RouteStartUTC":"2018-01-09T18:00:00Z","ScheduleId":"offline-2018-01-10","Unique":"zzz-offline-2018-01-10","Completed":[[17]]}},"LatestScheduleId":"offline-2018-01-30","Material":[{"Action":{"Type":0},"JobUnique":"ccc-offline-2018-01-10","Location":{"Face":2,"Pallet":"4","Type":1},"MaterialID":985,"PartName":"ccc","Path":1,"Process":2,"Serial":"00000000fT","SignaledInspections":[],"WorkorderId":""},{"Action":{"Type":0},"JobUnique":"zzz-offline-2018-01-10","Location":{"Face":1,"Pallet":"8","Type":1},"MaterialID":989,"PartName":"zzz","Path":1,"Process":1,"Serial":"00000000fX","SignaledInspections":[],"WorkorderId":""},{"Action":{"Type":0},"JobUnique":"zzz-offline-2018-01-10","Location":{"Face":1,"Pallet":"6","Type":1},"MaterialID":990,"PartName":"zzz","Path":1,"Process":1,"Serial":"00000000fY","SignaledInspections":[],"WorkorderId":""},{"Action":{"Type":0},"JobUnique":"ccc-offline-2018-01-10","Location":{"Face":2,"Pallet":"2","Type":1},"MaterialID":992,"PartName":"ccc","Path":1,"Process":2,"Serial":"00000000g0","SignaledInspections":[],"WorkorderId":""},{"Action":{"ElapsedMachiningTime":"PT51M59.3464866S","ExpectedRemainingMachiningTime":"PT25M0.6535134S","Program":"500","Type":4},"JobUnique":"zzz-offline-2018-01-10","Location":{"Face":1,"Pallet":"7","Type":1},"MaterialID":994,"PartName":"zzz","Path":1,"Process":1,"Serial":"00000000g2","SignaledInspections":[],"WorkorderId":""},{"Action":{"Type":0},"JobUnique":"bbb-offline-2018-01-10","Location":{"Face":2,"Pallet":"1","Type":1},"MaterialID":995,"PartName":"bbb","Path":1,"Process":2,"Serial":"00000000g3","SignaledInspections":[],"WorkorderId":""},{"Action":{"Type":0},"JobUnique":"bbb-offline-2018-01-10","Location":{"Face":1,"Pallet":"4","Type":1},"MaterialID":996,"PartName":"bbb","Path":1,"Process":1,"Serial":"00000000g4","SignaledInspections":[],"WorkorderId":""},{"Action":{"Type":0},"JobUnique":"zzz-offline-2018-01-10","Location":{"Face":1,"Pallet":"5","Type":1},"MaterialID":997,"PartName":"zzz","Path":1,"Process":1,"Serial":"00000000g5","SignaledInspections":[],"WorkorderId":""},{"Action":{"Type":0},"JobUnique":"bbb-offline-2018-01-10","Location":{"Face":2,"Pallet":"3","Type":1},"MaterialID":998,"PartName":"bbb","Path":1,"Process":2,"Serial":"00000000g6","SignaledInspections":[],"WorkorderId":""},{"Action":{"Type":0},"JobUnique":"bbb-offline-2018-01-10","Location":{"Face":1,"Pallet":"2","Type":1},"MaterialID":999,"PartName":"bbb","Path":1,"Process":1,"Serial":"00000000g7","SignaledInspections":[],"WorkorderId":""},{"Action":{"ElapsedMachiningTime":"PT13M42.486287S","ExpectedRemainingMachiningTime":"PT0S","Program":"300","Type":4},"JobUnique":"bbb-offline-2018-01-10","Location":{"Face":1,"Pallet":"1","Type":1},"MaterialID":1000,"PartName":"bbb","Path":1,"Process":1,"Serial":"00000000g8","SignaledInspections":[],"WorkorderId":""},{"Action":{"Type":0},"JobUnique":"bbb-offline-2018-01-10","Location":{"Face":1,"Pallet":"3","Type":1},"MaterialID":1001,"PartName":"bbb","Path":1,"Process":1,"Serial":"00000000g9","SignaledInspections":[],"WorkorderId":""}],"Pallets":{"1":{"CurrentPalletLocation":{"group":"Machine","loc":1,"num":1},"FixtureOnPallet":"f10b9a9c-181b-5151-bd24-1de41f19cdde","NumFaces":2,"OnHold":false,"Pallet":"1"},"2":{"CurrentPalletLocation":{"group":"Machine","loc":2,"num":2},"FixtureOnPallet":"f10b9a9c-181b-5151-bd24-1de41f19cdde","NumFaces":2,"OnHold":false,"Pallet":"2"},"3":{"CurrentPalletLocation":{"group":"Machine","loc":2,"num":1},"FixtureOnPallet":"f10b9a9c-181b-5151-bd24-1de41f19cdde","NumFaces":2,"OnHold":false,"Pallet":"3"},"4":{"CurrentPalletLocation":{"group":"Machine","loc":2,"num":4},"FixtureOnPallet":"f10b9a9c-181b-5151-bd24-1de41f19cdde","NumFaces":2,"OnHold":false,"Pallet":"4"},"5":{"CurrentPalletLocation":{"group":"Machine","loc":2,"num":3},"FixtureOnPallet":"f10b9a9c-181b-5151-bd24-1de41f19cdde","NumFaces":1,"OnHold":false,"Pallet":"5"},"6":{"CurrentPalletLocation":{"group":"Machine","loc":1,"num":3},"FixtureOnPallet":"f10b9a9c-181b-5151-bd24-1de41f19cdde","NumFaces":1,"OnHold":false,"Pallet":"6"},"7":{"CurrentPalletLocation":{"group":"Machine","loc":1,"num":2},"FixtureOnPallet":"f10b9a9c-181b-5151-bd24-1de41f19cdde","NumFaces":1,"OnHold":false,"Pallet":"7"},"8":{"CurrentPalletLocation":{"group":"Machine","loc":1,"num":4},"FixtureOnPallet":"f10b9a9c-181b-5151-bd24-1de41f19cdde","NumFaces":1,"OnHold":false,"Pallet":"8"}},"Queues":{}}
